{
			"RB_ARBR_AA": {
				"info": {
					"code": "RB_ARBR_AA",
					"name": "Above Red Butte Reservoir Advanced Aquatic",
					"latitude": "40.779602",
					"longitude": "-111.806669",
					"lat_long_datum": "WGS84",
					"elevation": "1648.6632",
					"local_x": "None",
					"local_y": "None",
					"local_projection": "None",
					"pos_accuracy": "None",
					"state": "Utah",
					"county": "Salt Lake",
					"comments": "",
					"type": "Stream"
					},

				"update_time": {
					"min": "2013-08-30 12:30:00",
					"max": "2014-05-28 12:45:00"
					},

				"vars": [
							{
							"name": "Battery voltage",
							"unit": "V",
							"code": "BattVolt",
							"values": [14.03, 14.08, 14.07, 14.06, 14.07, 14.08, 14.09, 14.22, 14.18, 14.19]
							},
							{
							"name": "Relative Humidity",
							"unit": "%",
							"code": "RH_enc",
							"values": [19.7, 19.74, 19.74, 19.71, 19.81, 19.78, 19.98, 19.78, 20.25, 20.7]
							},
							{
							"name": "Indicator",
							"unit": "code",
							"code": "Door_Tot",
							"values": [0.0, 0.0, 0.0, 0.0, 0.0, 0.0, 0.0, 0.0, 0.0, 0.0]
							},
							{
							"name": "Temperature",
							"unit": "degC",
							"code": "WaterTemp_EXO",
							"values": [12.52, 12.33, 12.06, 11.8, 11.67, 11.53, 11.32, 11.11, 11.02, 10.87]
							},
							{
							"name": "Specific Conductance",
							"unit": "uS/cm",
							"code": "SpCond",
							"values": [589.4, 590.0, 590.9, 591.8, 592.5, 593.3, 593.9, 594.4, 594.8, 595.2]
							},
							{
							"name": "pH",
							"unit": "pH",
							"code": "pH",
							"values": [8.57, 8.57, 8.56, 8.56, 8.56, 8.56, 8.55, 8.55, 8.55, 8.54]
							},
							{
							"name": "Oxygen, dissolved",
							"unit": "mg/L",
							"code": "ODO",
							"values": [8.66, 8.73, 8.77, 8.86, 8.86, 8.9, 8.95, 8.98, 8.99, 9.03]
							},
							{
							"name": "Oxygen, dissolved percent of saturation",
							"unit": "% Sat",
							"code": "ODO_Sat",
							"values": [81.5, 81.7, 81.7, 81.9, 81.7, 81.9, 81.9, 81.8, 81.7, 81.8]
							},
							{
							"name": "Oxygen, dissolved, transducer signal",
							"unit": "% Sat",
							"code": "ODO_Local",
							"values": [98.1, 98.4, 98.3, 98.6, 98.4, 98.6, 98.6, 98.5, 98.3, 98.5]
							},
							{
							"name": "Time Stamp",
							"unit": "hhmm",
							"code": "EXOTime",
							"values": [194221.0, 192721.0, 191221.0, 185721.0, 184221.0, 182721.0, 181221.0, 175721.0, 174221.0, 172721.0]
							},
							{
							"name": "Electric Power",
							"unit": "V",
							"code": "EXOVolt",
							"values": [13.59, 13.59, 13.59, 13.61, 13.54, 13.6, 13.66, 13.68, 13.71, 13.64]
							},
							{
							"name": "Turbidity",
							"unit": "NTU",
							"code": "TurbAvg",
							"values": [11.19, 7.62, 16.21, 6.67, 7.43, 6.12, 7.04, 6.4, 7.11, 6.61]
							},
							{
							"name": "Turbidity",
							"unit": "NTU",
							"code": "TurbMed",
							"values": [11.02, 7.36, 15.65, 6.27, 7.02, 6.11, 6.97, 6.18, 6.63, 6.41]
							},
							{
							"name": "Turbidity",
							"unit": "NTU",
							"code": "TurbMin",
							"values": [8.8, 5.6, 12.28, 4.96, 5.43, 4.71, 4.76, 4.86, 4.77, 4.9]
							},
							{
							"name": "Turbidity",
							"unit": "NTU",
							"code": "TurbMax",
							"values": [14.86, 14.91, 28.3, 12.95, 22.53, 10.52, 10.89, 10.6, 18.0, 10.89]
							},
							{
							"name": "Turbidity",
							"unit": "NTU",
							"code": "TurbVar",
							"values": [1.57, 2.463, 7.345, 2.528, 5.06, 0.858, 1.788, 0.984, 3.692, 1.284]
							},
							{
							"name": "Turbidity",
							"unit": "NTU",
							"code": "TurbBES",
							"values": [11.08, 7.43, 15.74, 6.3, 7.02, 6.03, 6.92, 6.27, 6.71, 6.43]
							},
							{
							"name": "Temperature",
							"unit": "degC",
							"code": "WaterTemp_Turb",
							"values": [12.4, 12.2, 12.0, 11.7, 11.6, 11.5, 11.2, 11.1, 11.0, 10.8]
							},
							{
							"name": "Indicator",
							"unit": "code",
							"code": "TurbWipe",
							"values": [0.0, 0.0, 0.0, 0.0, 0.0, 0.0, 0.0, 0.0, 0.0, 0.0]
							},
							{
							"name": "Blue-green algae (cyanobacteria), phycocyanin",
							"unit": "RFU",
							"code": "BGA",
							"values": [-0.06, -0.05, -0.06, -0.05, -0.06, -0.05, -0.04, -0.04, -0.06, -0.08]
							},
							{
							"name": "Chlorophyll Fluorescence",
							"unit": "RFU",
							"code": "Chlorophyll",
							"values": [1.12, 0.97, 1.12, 1.16, 1.1, 1.02, 0.68, 0.71, 0.64, 0.69]
							},
							{
							"name": "Colored Dissolved Organic Matter",
							"unit": "QSU",
							"code": "fDOM",
							"values": [22.22, 20.8, 20.63, 21.42, 21.22, 20.86, 20.91, 21.09, 20.95, 21.4]
							}
					]

			},

			"RB_ARBR_C": {
				"info": {
					"code": "RB_ARBR_C",
					"name": "Above Red Butte Reservoir Climate",
					"latitude": "40.780567",
					"longitude": "-111.807222",
					"lat_long_datum": "WGS84",
					"elevation": "1666.0368",
					"local_x": "None",
					"local_y": "None",
					"local_projection": "None",
					"pos_accuracy": "None",
					"state": "Utah",
					"county": "Salt Lake",
					"comments": "",
					"type": "Atmosphere"
					},

				"update_time": {
					"min": "2013-06-19 13:45:00",
					"max": "2014-05-28 13:00:00"
					},

				"vars": [
							{
							"name": "Temperature",
							"unit": "degC",
							"code": "AirTemp_Avg",
							"values": [27.33, 26.74, 26.88, 26.34, 25.85, 25.82, 26.17, 25.67, 25.14, 24.83]
							},
							{
							"name": "Relative Humidity",
							"unit": "%",
							"code": "RH",
							"values": [16.25, 19.6, 18.68, 18.7, 21.78, 21.64, 19.52, 20.06, 21.63, 22.21]
							},
							{
							"name": "Temperature, dew point",
							"unit": "degC",
							"code": "DewPt_Avg",
							"values": [2.125, 2.21, 2.263, 2.829, 2.965, 2.335, 2.162, 2.145, 2.827, 2.59]
							},
							{
							"name": "Vapor pressure",
							"unit": "kPa",
							"code": "VaporPress_Avg",
							"values": [0.713, 0.718, 0.719, 0.75, 0.757, 0.723, 0.715, 0.714, 0.749, 0.737]
							},
							{
							"name": "Barometric pressure",
							"unit": "kPa",
							"code": "BP_Avg",
							"values": [82.9, 82.9, 83.0, 83.0, 83.0, 83.0, 83.0, 83.1, 83.1, 83.1]
							},
							{
							"name": "Wind speed",
							"unit": "m/s",
							"code": "WindSp_Avg",
							"values": [6.739, 5.162, 6.71, 4.831, 4.854, 5.541, 5.511, 5.628, 5.049, 4.215]
							},
							{
							"name": "Wind direction",
							"unit": "deg",
							"code": "WindDir_Avg",
							"values": [259.1, 264.5, 259.8, 261.2, 259.7, 256.5, 268.2, 255.8, 258.8, 248.8]
							},
							{
							"name": "Wind direction",
							"unit": "deg",
							"code": "WindDir_Std",
							"values": [20.68, 21.79, 15.39, 30.87, 21.21, 20.68, 19.8, 15.52, 15.98, 21.8]
							},
							{
							"name": "Precipitation",
							"unit": "cm",
							"code": "Precip_Tot_Avg",
							"values": [48.85, 48.85, 48.85, 48.85, 48.85, 48.85, 48.85, 48.85, 48.85, 48.85]
							},
							{
							"name": "Precipitation",
							"unit": "Hz",
							"code": "Precip_Freq_Avg",
							"values": [1954.0, 1954.0, 1954.0, 1954.0, 1954.0, 1954.0, 1954.0, 1954.0, 1954.0, 1954.0]
							},
							{
							"name": "Snow depth",
							"unit": "cm",
							"code": "JuddDepth_Avg",
							"values": [2.894, 2.768, 6.414, 4.049, 2.838, 12.61, 13.21, 3.725, 14.29, 3.605]
							},
							{
							"name": "Temperature",
							"unit": "degC",
							"code": "JuddTemp_Avg",
							"values": [29.2, 28.64, 28.66, 28.35, 27.79, 27.64, 27.87, 27.45, 27.12, 26.6]
							},
							{
							"name": "Radiation, incoming shortwave",
							"unit": "W/m^2",
							"code": "SWIn_NR01_Avg",
							"values": [1018.0, 854.0, 950.0, 905.0, 921.0, 787.1, 910.0, 923.0, 943.0, 543.3]
							},
							{
							"name": "Radiation, outgoing shortwave",
							"unit": "W/m^2",
							"code": "SWOut_NR01_Avg",
							"values": [168.5, 141.8, 154.3, 146.7, 152.1, 129.7, 148.1, 150.7, 157.9, 89.0]
							},
							{
							"name": "Radiation, incoming longwave",
							"unit": "W/m^2",
							"code": "LWIn_Cor_NR01_Avg",
							"values": [357.0, 358.5, 348.2, 350.1, 350.6, 347.4, 341.9, 341.2, 338.7, 348.4]
							},
							{
							"name": "Radiation, outgoing longwave",
							"unit": "W/m^2",
							"code": "LWOut_Cor_NR01_Avg",
							"values": [532.5, 517.6, 526.1, 520.1, 512.0, 505.5, 515.2, 507.7, 499.3, 475.7]
							},
							{
							"name": "Radiation, net",
							"unit": "W/m^2",
							"code": "NetRad_NR01_Avg",
							"values": [674.0, 553.2, 618.3, 588.0, 607.5, 499.3, 588.5, 606.2, 624.4, 327.0]
							},
							{
							"name": "Radiation, incoming longwave",
							"unit": "W/m^2",
							"code": "LWIn_UnCor_NR01_Avg",
							"values": [-120.3, -115.0, -126.3, -123.6, -117.4, -120.4, -127.0, -125.8, -123.8, -115.4]
							},
							{
							"name": "Radiation, outgoing longwave",
							"unit": "W/m^2",
							"code": "LWOut_UnCor_NR01_Avg",
							"values": [55.11, 44.11, 51.53, 46.38, 43.97, 37.74, 46.35, 40.73, 36.85, 11.89]
							},
							{
							"name": "Temperature, sensor",
							"unit": "degC",
							"code": "Temp_NR01_Avg",
							"values": [29.76, 29.15, 29.31, 29.18, 28.28, 28.23, 28.41, 28.1, 27.37, 27.58]
							},
							{
							"name": "Radiation, incoming shortwave",
							"unit": "W/m^2",
							"code": "SWIn_SP230_Avg",
							"values": [999.0, 841.0, 922.0, 882.0, 899.0, 761.7, 875.0, 885.0, 901.0, 529.2]
							},
							{
							"name": "Indicator",
							"unit": "code",
							"code": "Heater_on",
							"values": [0.0, 0.0, 0.0, 0.0, 0.0, 0.0, 0.0, 0.0, 0.0, 0.0]
							},
							{
							"name": "Temperature",
							"unit": "degC",
							"code": "DeltaTemp",
							"values": [27.63, 26.93, 27.05, 26.36, 25.3, 25.9, 26.25, 25.96, 24.53, 25.01]
							},
							{
							"name": "Radiation, incoming PAR",
							"unit": "umol/m^2 s",
							"code": "PARIn_Avg",
							"values": [1907.0, 1606.0, 1787.0, 1700.0, 1721.0, 1463.0, 1681.0, 1700.0, 1728.0, 1021.0]
							},
							{
							"name": "Radiation, outgoing PAR",
							"unit": "umol/m^2 s",
							"code": "PAROut_Avg",
							"values": [122.0, 103.5, 115.5, 109.4, 110.9, 95.2, 109.3, 110.2, 112.7, 67.14]
							},
							{
							"name": "Temperature",
							"unit": "degC",
							"code": "TargTemp_SI111_Avg",
							"values": [31.55, 29.96, 30.79, 29.99, 29.39, 28.57, 29.67, 29.04, 28.3, 24.95]
							},
							{
							"name": "Temperature, sensor",
							"unit": "degC",
							"code": "Temp_SI111_Avg",
							"values": [28.91, 28.35, 28.53, 28.48, 27.7, 27.63, 27.82, 27.61, 26.99, 27.18]
							},
							{
							"name": "Slope",
							"unit": "-",
							"code": "m_SI111",
							"values": [1678264000.0, 1672036000.0, 1668123000.0, 1669611000.0, 1671734000.0, 1658608000.0, 1661030000.0, 1661897000.0, 1661434000.0, 1644744000.0]
							},
							{
							"name": "Intercept",
							"unit": "-",
							"code": "b_SI111",
							"values": [6054255.0, 5873735.0, 5760544.0, 5803561.0, 5864992.0, 5486027.0, 5555809.0, 5580811.0, 5567436.0, 5087942.0]
							},
							{
							"name": "Voltage",
							"unit": "mV",
							"code": "TargV_SI111_Avg",
							"values": [0.173, 0.104, 0.147, 0.097, 0.109, 0.059, 0.119, 0.092, 0.083, -0.147]
							},
							{
							"name": "Volumetric water content",
							"unit": "-",
							"code": "VWC_5cm_Avg",
							"values": [11.72, 11.72, 11.72, 11.66, 11.6, 11.6, 11.54, 11.6, 11.54, 11.49]
							},
							{
							"name": "Temperature",
							"unit": "degC",
							"code": "SoilTemp_5cm_Avg",
							"values": [31.08, 30.72, 30.01, 29.25, 28.88, 28.16, 27.12, 25.97, 25.28, 23.62]
							},
							{
							"name": "Bulk electrical conductivity",
							"unit": "dS/m",
							"code": "SoilCond_5cm_Avg",
							"values": [0.311, 0.32, 0.33, 0.311, 0.301, 0.29, 0.29, 0.271, 0.27, 0.251]
							},
							{
							"name": "Permittivity",
							"unit": "-",
							"code": "Permittivity_5cm_Avg",
							"values": [6.25, 6.25, 6.25, 6.221, 6.201, 6.201, 6.171, 6.199, 6.171, 6.151]
							},
							{
							"name": "Volumetric water content",
							"unit": "-",
							"code": "VWC_10cm_Avg",
							"values": [17.04, 17.04, 17.05, 17.16, 17.27, 17.32, 17.1, 17.21, 17.16, 17.26]
							},
							{
							"name": "Temperature",
							"unit": "degC",
							"code": "SoilTemp_10cm_Avg",
							"values": [20.49, 20.23, 20.03, 19.81, 19.66, 19.48, 19.35, 19.26, 19.19, 19.15]
							},
							{
							"name": "Bulk electrical conductivity",
							"unit": "dS/m",
							"code": "SoilCond_10cm_Avg",
							"values": [0.699, 0.69, 0.689, 0.671, 0.67, 0.603, 0.649, 0.65, 0.631, 0.65]
							},
							{
							"name": "Permittivity",
							"unit": "-",
							"code": "Permittivity_10cm_Avg",
							"values": [8.7, 8.7, 8.71, 8.76, 8.82, 8.85, 8.73, 8.79, 8.76, 8.82]
							},
							{
							"name": "Volumetric water content",
							"unit": "-",
							"code": "VWC_20cm_Avg",
							"values": [23.12, 23.69, 23.13, 23.24, 23.3, 23.52, 23.47, 23.52, 23.25, 23.69]
							},
							{
							"name": "Temperature",
							"unit": "degC",
							"code": "SoilTemp_20cm_Avg",
							"values": [18.82, 18.82, 18.82, 18.82, 18.82, 18.84, 18.88, 18.88, 18.91, 18.91]
							},
							{
							"name": "Bulk electrical conductivity",
							"unit": "dS/m",
							"code": "SoilCond_20cm_Avg",
							"values": [1.08, 1.051, 1.089, 1.09, 1.061, 1.08, 1.08, 1.09, 1.099, 1.081]
							},
							{
							"name": "Permittivity",
							"unit": "-",
							"code": "Permittivity_20cm_Avg",
							"values": [12.04, 12.38, 12.05, 12.11, 12.14, 12.27, 12.25, 12.28, 12.12, 12.38]
							},
							{
							"name": "Volumetric water content",
							"unit": "-",
							"code": "VWC_50cm_Avg",
							"values": [21.14, 21.37, 21.48, 21.37, 21.21, 21.14, 21.37, 21.21, 21.09, 21.42]
							},
							{
							"name": "Temperature",
							"unit": "degC",
							"code": "SoilTemp_50cm_Avg",
							"values": [16.13, 16.13, 16.13, 16.13, 16.08, 16.11, 16.11, 16.11, 16.06, 16.06]
							},
							{
							"name": "Bulk electrical conductivity",
							"unit": "dS/m",
							"code": "SoilCond_50cm_Avg",
							"values": [0.97, 0.96, 0.97, 0.97, 0.97, 0.97, 0.951, 0.979, 0.98, 0.97]
							},
							{
							"name": "Permittivity",
							"unit": "-",
							"code": "Permittivity_50cm_Avg",
							"values": [10.89, 11.01, 11.08, 11.02, 10.92, 10.89, 11.01, 10.92, 10.85, 11.04]
							},
							{
							"name": "Volumetric water content",
							"unit": "-",
							"code": "VWC_100cm_Avg",
							"values": [23.27, 23.81, 23.15, 23.84, 23.58, 23.5, 23.31, 23.92, 23.87, 23.98]
							},
							{
							"name": "Temperature",
							"unit": "degC",
							"code": "SoilTemp_100cm_Avg",
							"values": [12.82, 13.12, 13.12, 13.12, 13.14, 13.09, 13.09, 12.94, 13.12, 13.09]
							},
							{
							"name": "Bulk electrical conductivity",
							"unit": "dS/m",
							"code": "SoilCond_100cm_Avg",
							"values": [1.016, 1.05, 1.069, 1.06, 1.06, 1.05, 1.05, 1.047, 1.05, 1.05]
							},
							{
							"name": "Permittivity",
							"unit": "-",
							"code": "Permittivity_100cm_Avg",
							"values": [12.17, 12.45, 12.06, 12.47, 12.32, 12.27, 12.15, 12.54, 12.49, 12.56]
							},
							{
							"name": "Battery voltage",
							"unit": "V",
							"code": "BattVolt",
							"values": [13.2, 13.3, 13.18, 13.15, 13.16, 13.62, 13.58, 13.63, 13.68, 13.56]
							},
							{
							"name": "Temperature, datalogger",
							"unit": "degC",
							"code": "Panel_Temp",
							"values": [30.49, 30.3, 30.36, 30.2, 29.82, 29.83, 29.8, 29.4, 28.78, 28.39]
							},
							{
							"name": "Relative Humidity",
							"unit": "%",
							"code": "RH_enc",
							"values": [55.9, 56.86, 56.32, 55.59, 55.47, 56.51, 56.17, 55.6, 55.72, 57.66]
							},
							{
							"name": "Indicator",
							"unit": "code",
							"code": "Door_Tot",
							"values": [0.0, 0.0, 0.0, 0.0, 0.0, 0.0, 0.0, 0.0, 0.0, 0.0]
							},
							{
							"name": "Counter",
							"unit": "#",
							"code": "n",
							"values": [87.0, 87.0, 87.0, 87.0, 87.0, 87.0, 87.0, 87.0, 87.0, 87.0]
							},
							{
							"name": "Offset",
							"unit": "cm",
							"code": "JuddOffset",
							"values": [239.0, 239.0, 239.0, 239.0, 239.0, 239.0, 239.0, 239.0, 239.0, 239.0]
							},
							{
							"name": "Snow depth",
							"unit": "cm",
							"code": "JuddDepth_1",
							"values": [2.546, 21.21, 3.525, 3.114, 4.301, 3.316, 4.995, 1.911, 3.79, 12.73]
							},
							{
							"name": "Snow depth",
							"unit": "cm",
							"code": "JuddDepth_2",
							"values": [25.52, 3.529, 4.592, 2.622, 4.343, 3.48, 10.21, 2.732, 3.257, 1.814]
							},
							{
							"name": "Snow depth",
							"unit": "cm",
							"code": "JuddDepth_3",
							"values": [4.598, 4.473, 6.069, 3.073, 5.778, 3.686, 4.011, 4.783, 11.46, 0.829]
							},
							{
							"name": "Temperature",
							"unit": "degC",
							"code": "AirTemp_ST110_Avg",
							"values": [28.19, 27.51, 27.59, 27.13, 26.74, 26.52, 26.66, 26.4, 26.03, 25.3]
							},
							{
							"name": "Temperature",
							"unit": "degC",
							"code": "AirTemp_ST110_Max",
							"values": [28.97, 28.05, 28.11, 27.73, 27.85, 27.33, 27.13, 26.94, 26.77, 25.94]
							},
							{
							"name": "Temperature",
							"unit": "degC",
							"code": "AirTemp_ST110_Min",
							"values": [27.63, 26.92, 27.08, 26.8, 25.74, 25.77, 26.05, 25.91, 25.31, 24.65]
							},
							{
							"name": "Offset",
							"unit": "cm",
							"code": "Precip_offset",
							"values": [26.77, 26.77, 26.77, 26.77, 26.77, 26.77, 26.77, 26.77, 26.77, 26.77]
							},
							{
							"name": "Precipitation",
							"unit": "cm",
							"code": "Precip_HrDiff",
							"values": [0.0, 0.0, 0.0, 0.0, 0.0, 0.0, 0.0, 0.0, 0.0, 0.0]
							},
							{
							"name": "Evapotranspiration, potential",
							"unit": "mm",
							"code": "Evapotrans_ETr",
							"values": [0.7455617, 0.6008155, 0.7163723, 0.5750071, 0.5697918, 0.5936322, 0.6148373, 0.6187404, 0.5703642, 0.4446603]
							},
							{
							"name": "Evapotranspiration, potential",
							"unit": "mm",
							"code": "Evapotrans_ETo",
							"values": [0.497817, 0.4054119, 0.4756213, 0.3929587, 0.3903923, 0.3950207, 0.4142867, 0.4167136, 0.3897329, 0.2945145]
							},
							{
							"name": "Temperature, sensor",
							"unit": "degC",
							"code": "InletTemp_avg",
							"values": [-242.0, -242.0, -242.0, -242.0, -242.0, -242.0, -242.0, -242.0, -242.0, -242.0]
							},
							{
							"name": "Frequency of rotation",
							"unit": "rpm",
							"code": "Tachometer_TS100",
							"values": [4686.0, 4693.0, 4693.0, 4692.0, 4722.0, 4828.0, 4826.0, 4830.0, 4844.0, 4850.0]
							},
							{
							"name": "Counter",
							"unit": "#",
							"code": "GeonorHeater_Tot",
							"values": [0.0, 0.0, 0.0, 0.0, 0.0, 0.0, 0.0, 0.0, 0.0, 0.0]
							},
							{
							"name": "Counter",
							"unit": "#",
							"code": "GeonorHeater_Manual_Tot",
							"values": [0.0, 0.0, 0.0, 0.0, 0.0, 0.0, 0.0, 0.0, 0.0, 0.0]
							}
					]

			},

			"RB_ARBR_USGS": {
				"info": {
					"code": "RB_ARBR_USGS",
					"name": "USGS Gage 10172200 above Red Butte Reservoir",
					"latitude": "40.78",
					"longitude": "-111.805278",
					"lat_long_datum": "WGS84",
					"elevation": "1646.0",
					"local_x": "None",
					"local_y": "None",
					"local_projection": "None",
					"pos_accuracy": "None",
					"state": "Utah",
					"county": "Salt Lake",
					"comments": "on right bank 0.4 miles upstream from dam forming Red Butte Reservoir and 1.7 miles  northeast of Fort Douglas",
					"type": "Stream"
					},

				"update_time": {
					"min": "2013-07-01 01:30:00",
					"max": "2014-05-28 16:45:00"
					},

				"vars": [
							{
							"name": "Gage Height",
							"unit": "ft",
							"code": "USGSStage",
							"values": [0.4, 0.4, 0.4, 0.4, 0.4, 0.4, 0.4, 0.4, 0.4, 0.41]
							},
							{
							"name": "Discharge",
							"unit": "cfs",
							"code": "USGSDischarge",
							"values": [2.1, 2.1, 2.1, 2.1, 2.1, 2.1, 2.1, 2.1, 2.1, 2.2]
							},
							{
							"name": "Temperature",
							"unit": "degC",
							"code": "USGSTemp",
							"values": [13.0, 13.1, 13.2, 13.2, 13.2, 13.2, 13.0, 13.0, 13.0, 13.1]
							}
					]

			},

			"RB_CG_BA": {
				"info": {
					"code": "RB_CG_BA",
					"name": "Cottams Grove Basic Aquatic",
					"latitude": "40.763958",
					"longitude": "-111.828286",
					"lat_long_datum": "WGS84",
					"elevation": "1502.3592",
					"local_x": "None",
					"local_y": "None",
					"local_projection": "None",
					"pos_accuracy": "None",
					"state": "Utah",
					"county": "Salt Lake",
					"comments": "",
					"type": "Stream"
					},

				"update_time": {
					"min": "2013-08-14 13:36:00",
					"max": "2014-05-28 15:45:00"
					},

				"vars": [
							{
							"name": "Battery voltage",
							"unit": "V",
							"code": "BattVolt",
							"values": [13.54, 13.48, 13.48, 13.48, 13.44, 13.45, 13.44, 13.44, 13.42, 13.36]
							},
							{
							"name": "Relative Humidity",
							"unit": "%",
							"code": "RH_enc",
							"values": [33.21, 34.29, 34.05, 33.92, 32.76, 31.54, 29.43, 28.14, 25.02, 20.88]
							},
							{
							"name": "Indicator",
							"unit": "code",
							"code": "Door_Tot",
							"values": [0.0, 0.0, 0.0, 0.0, 0.0, 0.0, 0.0, 0.0, 0.0, 0.0]
							},
							{
							"name": "Temperature",
							"unit": "degC",
							"code": "WaterTemp_EXO",
							"values": [14.25, 14.34, 14.4, 14.45, 14.43, 14.4, 14.34, 14.32, 14.34, 14.39]
							},
							{
							"name": "Specific Conductance",
							"unit": "uS/cm",
							"code": "SpCond",
							"values": [576.4, 576.4, 576.3, 576.2, 576.4, 576.5, 576.7, 577.7, 577.7, 577.9]
							},
							{
							"name": "pH",
							"unit": "pH",
							"code": "pH",
							"values": [8.49, 8.5, 8.5, 8.5, 8.51, 8.51, 8.51, 8.51, 8.52, 8.52]
							},
							{
							"name": "Oxygen, dissolved",
							"unit": "mg/L",
							"code": "ODO",
							"values": [8.7, 8.7, 8.71, 8.71, 8.71, 8.74, 8.75, 8.75, 8.75, 8.76]
							},
							{
							"name": "Oxygen, dissolved percent of saturation",
							"unit": "% Sat",
							"code": "ODO_Sat",
							"values": [85.1, 85.2, 85.4, 85.5, 85.4, 85.7, 85.6, 85.7, 85.7, 85.9]
							},
							{
							"name": "Oxygen, dissolved, transducer signal",
							"unit": "% Sat",
							"code": "ODO_Local",
							"values": [100.7, 100.8, 101.0, 101.2, 101.1, 101.5, 101.4, 101.4, 101.4, 101.6]
							},
							{
							"name": "Time Stamp",
							"unit": "hhmm",
							"code": "EXOTime",
							"values": [224349.0, 222850.0, 221350.0, 215850.0, 214349.0, 212849.0, 211350.0, 205849.0, 204350.0, 202849.0]
							},
							{
							"name": "Electric Power",
							"unit": "V",
							"code": "EXOVolt",
							"values": [13.11, 13.08, 13.05, 13.05, 13.02, 13.02, 13.02, 13.03, 12.99, 12.97]
							},
							{
							"name": "Turbidity",
							"unit": "NTU",
							"code": "TurbAvg",
							"values": [23.02, 21.33, 21.17, 21.17, 21.15, 20.92, 21.43, 21.44, 21.46, 20.59]
							},
							{
							"name": "Turbidity",
							"unit": "NTU",
							"code": "TurbMed",
							"values": [22.38, 21.12, 20.97, 20.81, 20.91, 20.87, 21.05, 21.21, 21.25, 20.42]
							},
							{
							"name": "Turbidity",
							"unit": "NTU",
							"code": "TurbMin",
							"values": [18.74, 17.38, 17.66, 17.44, 17.35, 17.39, 18.84, 18.44, 17.96, 17.65]
							},
							{
							"name": "Turbidity",
							"unit": "NTU",
							"code": "TurbMax",
							"values": [37.09, 26.68, 25.98, 40.56, 26.07, 29.65, 26.75, 27.66, 29.47, 26.35]
							},
							{
							"name": "Turbidity",
							"unit": "NTU",
							"code": "TurbVar",
							"values": [9.24, 3.334, 3.334, 9.74, 3.167, 3.851, 2.359, 3.641, 3.48, 2.393]
							},
							{
							"name": "Turbidity",
							"unit": "NTU",
							"code": "TurbBES",
							"values": [22.43, 21.2, 21.04, 20.77, 20.97, 20.8, 21.24, 21.2, 21.23, 20.44]
							},
							{
							"name": "Temperature",
							"unit": "degC",
							"code": "WaterTemp_Turb",
							"values": [14.4, 14.5, 14.5, 14.6, 14.6, 14.5, 14.5, 14.5, 14.5, 14.6]
							},
							{
							"name": "Indicator",
							"unit": "code",
							"code": "TurbWipe",
							"values": [0.0, 0.0, 0.0, 0.0, 0.0, 0.0, 0.0, 0.0, 0.0, 0.0]
							},
							{
							"name": "Gage height",
							"unit": "cm",
							"code": "Stage",
							"values": [28.69, 28.72, 28.78, 28.78, 28.75, 28.79, 28.76, 28.8, 28.78, 28.85]
							},
							{
							"name": "Temperature",
							"unit": "degC",
							"code": "WaterTemp_PT",
							"values": [14.18, 14.27, 14.33, 14.36, 14.35, 14.3, 14.25, 14.25, 14.26, 14.32]
							},
							{
							"name": "Counter",
							"unit": "#",
							"code": "StageNaNCounter",
							"values": [0.0, 0.0, 0.0, 0.0, 0.0, 0.0, 0.0, 0.0, 0.0, 0.0]
							},
							{
							"name": "Offset",
							"unit": "cm",
							"code": "StageOffset",
							"values": [0.0, 0.0, 0.0, 0.0, 0.0, 0.0, 0.0, 0.0, 0.0, 0.0]
							}
					]

			},

			"RB_FD_AA": {
				"info": {
					"code": "RB_FD_AA",
					"name": "Foothill Drive Advanced Aquatic",
					"latitude": "40.757225",
					"longitude": "-111.833722",
					"lat_long_datum": "WGS84",
					"elevation": "1449.324",
					"local_x": "None",
					"local_y": "None",
					"local_projection": "None",
					"pos_accuracy": "None",
					"state": "Utah",
					"county": "Salt Lake",
					"comments": "",
					"type": "Stream"
					},

				"update_time": {
					"min": "2013-08-14 12:15:00",
					"max": "2014-05-28 15:45:00"
					},

				"vars": [
							{
							"name": "Battery voltage",
							"unit": "V",
							"code": "BattVolt",
							"values": [13.51, 13.51, 13.46, 13.5, 13.47, 13.47, 13.46, 13.41, 13.37, 13.35]
							},
							{
							"name": "Relative Humidity",
							"unit": "%",
							"code": "RH_enc",
							"values": [20.93, 20.96, 21.0, 21.06, 21.06, 21.2, 21.2, 20.99, 20.31, 19.16]
							},
							{
							"name": "Indicator",
							"unit": "code",
							"code": "Door_Tot",
							"values": [0.0, 0.0, 0.0, 0.0, 0.0, 0.0, 0.0, 0.0, 0.0, 0.0]
							},
							{
							"name": "Temperature",
							"unit": "degC",
							"code": "WaterTemp_EXO",
							"values": [14.94, 15.02, 15.1, 15.19, 15.24, 15.3, 15.31, 15.36, 15.38, 15.49]
							},
							{
							"name": "Specific Conductance",
							"unit": "uS/cm",
							"code": "SpCond",
							"values": [588.3, 588.6, 589.1, 588.6, 589.0, 588.8, 589.4, 589.2, 588.7, 590.2]
							},
							{
							"name": "pH",
							"unit": "pH",
							"code": "pH",
							"values": [8.21, 8.22, 8.22, 8.23, 8.23, 8.23, 8.23, 8.24, 8.24, 8.25]
							},
							{
							"name": "Oxygen, dissolved",
							"unit": "mg/L",
							"code": "ODO",
							"values": [8.26, 8.29, 8.31, 8.34, 8.32, 8.35, 8.33, 8.33, 8.32, 8.4]
							},
							{
							"name": "Oxygen, dissolved percent of saturation",
							"unit": "% Sat",
							"code": "ODO_Sat",
							"values": [82.0, 82.3, 82.8, 83.2, 83.1, 83.5, 83.3, 83.4, 83.4, 84.3]
							},
							{
							"name": "Oxygen, dissolved, transducer signal",
							"unit": "% Sat",
							"code": "ODO_Local",
							"values": [96.6, 97.0, 97.5, 98.0, 97.8, 98.4, 98.1, 98.2, 98.2, 99.3]
							},
							{
							"name": "Time Stamp",
							"unit": "hhmm",
							"code": "EXOTime",
							"values": [224226.0, 222726.0, 221226.0, 215726.0, 214226.0, 212726.0, 211226.0, 205726.0, 204226.0, 202726.0]
							},
							{
							"name": "Electric Power",
							"unit": "V",
							"code": "EXOVolt",
							"values": [13.06, 13.07, 13.05, 13.05, 13.05, 13.06, 13.03, 12.99, 12.97, 12.94]
							},
							{
							"name": "Turbidity",
							"unit": "NTU",
							"code": "TurbAvg",
							"values": [17.68, 18.66, 18.64, 19.6, 17.71, 19.29, 20.33, 20.54, 19.31, 18.02]
							},
							{
							"name": "Turbidity",
							"unit": "NTU",
							"code": "TurbMed",
							"values": [17.41, 18.55, 18.33, 19.41, 17.56, 18.95, 20.5, 20.42, 18.95, 17.98]
							},
							{
							"name": "Turbidity",
							"unit": "NTU",
							"code": "TurbMin",
							"values": [14.79, 16.44, 16.11, 15.16, 14.68, 15.71, 16.79, 18.35, 16.45, 14.55]
							},
							{
							"name": "Turbidity",
							"unit": "NTU",
							"code": "TurbMax",
							"values": [23.78, 21.52, 23.75, 30.96, 21.94, 32.07, 24.36, 25.62, 25.57, 24.91]
							},
							{
							"name": "Turbidity",
							"unit": "NTU",
							"code": "TurbVar",
							"values": [2.979, 1.443, 2.666, 5.471, 3.151, 6.112, 2.574, 1.905, 3.148, 4.27]
							},
							{
							"name": "Turbidity",
							"unit": "NTU",
							"code": "TurbBES",
							"values": [17.36, 18.55, 18.38, 19.43, 17.57, 18.99, 20.38, 20.51, 19.08, 17.84]
							},
							{
							"name": "Temperature",
							"unit": "degC",
							"code": "WaterTemp_Turb",
							"values": [15.4, 15.5, 15.5, 15.6, 15.7, 15.7, 15.8, 15.8, 15.8, 15.9]
							},
							{
							"name": "Indicator",
							"unit": "code",
							"code": "TurbWipe",
							"values": [0.0, 0.0, 0.0, 0.0, 0.0, 0.0, 0.0, 0.0, 0.0, 0.0]
							},
							{
							"name": "Gage height",
							"unit": "cm",
							"code": "Stage",
							"values": [47.95, 47.86, 47.87, 47.86, 47.85, 47.85, 47.83, 47.66, 47.51, 47.26]
							},
							{
							"name": "Temperature",
							"unit": "degC",
							"code": "WaterTemp_PT",
							"values": [14.58, 14.6, 14.62, 14.63, 14.62, 14.6, 14.56, 14.51, 14.42, 14.29]
							},
							{
							"name": "Counter",
							"unit": "#",
							"code": "StageNaNCounter",
							"values": [0.0, 0.0, 0.0, 0.0, 0.0, 0.0, 0.0, 0.0, 0.0, 0.0]
							},
							{
							"name": "Offset",
							"unit": "cm",
							"code": "StageOffset",
							"values": [0.0, 0.0, 0.0, 0.0, 0.0, 0.0, 0.0, 0.0, 0.0, 0.0]
							},
							{
							"name": "Blue-green algae (cyanobacteria), phycocyanin",
							"unit": "RFU",
							"code": "BGA",
							"values": [0.17, 0.15, 0.15, 0.14, 0.14, 0.15, 0.17, 0.17, 0.17, 0.16]
							},
							{
							"name": "Chlorophyll Fluorescence",
							"unit": "RFU",
							"code": "Chlorophyll",
							"values": [0.75, 0.74, 0.81, 0.72, 0.72, 0.68, 0.73, 0.73, 0.73, 0.72]
							},
							{
							"name": "Colored Dissolved Organic Matter",
							"unit": "QSU",
							"code": "fDOM",
							"values": [22.19, 21.91, 21.77, 21.49, 21.69, 22.12, 21.76, 21.28, 21.14, 21.01]
							}
					]

			},

			"RB_GIRF_C": {
				"info": {
					"code": "RB_GIRF_C",
					"name": "Green Infrastructure Climate",
					"latitude": "40.7608",
					"longitude": "-111.830474",
					"lat_long_datum": "WGS84",
					"elevation": "1487.1192",
					"local_x": "None",
					"local_y": "None",
					"local_projection": "None",
					"pos_accuracy": "None",
					"state": "Utah",
					"county": "Salt Lake",
					"comments": "",
					"type": "Atmosphere"
					},

				"update_time": {
					"min": "2013-07-23 08:30:00",
					"max": "2014-05-28 16:00:00"
					},

				"vars": [
							{
							"name": "Temperature",
							"unit": "degC",
							"code": "AirTemp_Avg",
							"values": [29.76, 29.79, 30.06, 30.42, 30.56, 30.55, 30.26, 30.13, 30.09, 30.16]
							},
							{
							"name": "Relative Humidity",
							"unit": "%",
							"code": "RH",
							"values": [11.29, 11.17, 11.11, 10.53, 11.22, 14.03, 16.37, 15.16, 15.16, 15.58]
							},
							{
							"name": "Temperature, dew point",
							"unit": "degC",
							"code": "DewPt_Avg",
							"values": [-4.361, -3.545, -3.045, -3.17, -1.26, 0.618, 1.791, 1.008, 1.054, 0.857]
							},
							{
							"name": "Vapor pressure",
							"unit": "kPa",
							"code": "VaporPress_Avg",
							"values": [0.443, 0.471, 0.489, 0.484, 0.558, 0.639, 0.696, 0.657, 0.66, 0.65]
							},
							{
							"name": "Barometric pressure",
							"unit": "kPa",
							"code": "BP_Avg",
							"values": [84.6, 84.6, 84.6, 84.6, 84.6, 84.6, 84.6, 84.6, 84.6, 84.6]
							},
							{
							"name": "Wind speed",
							"unit": "m/s",
							"code": "WindSp_Avg",
							"values": [6.05, 5.639, 5.836, 6.046, 4.901, 3.961, 3.407, 4.102, 4.432, 4.164]
							},
							{
							"name": "Wind direction",
							"unit": "deg",
							"code": "WindDir_Avg",
							"values": [219.7, 208.6, 207.9, 214.3, 214.5, 206.4, 197.9, 191.8, 185.7, 185.9]
							},
							{
							"name": "Wind direction",
							"unit": "deg",
							"code": "WindDir_Std",
							"values": [16.71, 26.32, 21.41, 18.84, 24.17, 21.63, 23.66, 22.64, 26.28, 23.68]
							},
							{
							"name": "Precipitation",
							"unit": "cm",
							"code": "Precip_Tot_Avg",
							"values": [49.0, 49.0, 49.0, 49.0, 49.0, 49.0, 49.0, 49.0, 49.0, 49.0]
							},
							{
							"name": "Precipitation",
							"unit": "Hz",
							"code": "Precip_Freq_Avg",
							"values": [1918.0, 1918.0, 1918.0, 1918.0, 1918.0, 1918.0, 1918.0, 1918.0, 1918.0, 1918.0]
							},
							{
							"name": "Snow depth",
							"unit": "cm",
							"code": "JuddDepth_Avg",
							"values": [5.557, 7.027, 7.814, 7.011, 8.5, 7.445, 5.579, 6.285, 5.134, 7.181]
							},
							{
							"name": "Temperature",
							"unit": "degC",
							"code": "JuddTemp_Avg",
							"values": [30.16, 30.22, 30.52, 30.95, 31.2, 31.29, 30.94, 30.68, 30.67, 30.73]
							},
							{
							"name": "Radiation, incoming shortwave",
							"unit": "W/m^2",
							"code": "SWIn_NR01_Avg",
							"values": [248.2, 226.1, 302.7, 357.9, 393.3, 412.9, 500.1, 479.8, 453.7, 414.5]
							},
							{
							"name": "Radiation, outgoing shortwave",
							"unit": "W/m^2",
							"code": "SWOut_NR01_Avg",
							"values": [51.22, 46.84, 60.44, 70.34, 76.69, 79.29, 96.4, 92.4, 87.0, 78.06]
							},
							{
							"name": "Radiation, incoming longwave",
							"unit": "W/m^2",
							"code": "LWIn_Cor_NR01_Avg",
							"values": [372.7, 376.2, 379.6, 376.8, 375.7, 374.4, 369.4, 376.4, 379.6, 379.1]
							},
							{
							"name": "Radiation, outgoing longwave",
							"unit": "W/m^2",
							"code": "LWOut_Cor_NR01_Avg",
							"values": [467.7, 468.0, 473.1, 477.0, 479.2, 482.7, 485.7, 484.1, 484.2, 486.7]
							},
							{
							"name": "Radiation, net",
							"unit": "W/m^2",
							"code": "NetRad_NR01_Avg",
							"values": [102.0, 87.4, 148.8, 187.3, 213.2, 225.4, 287.4, 279.7, 262.1, 228.9]
							},
							{
							"name": "Radiation, incoming longwave",
							"unit": "W/m^2",
							"code": "LWIn_UnCor_NR01_Avg",
							"values": [-105.1, -102.4, -101.8, -107.6, -109.7, -113.0, -115.6, -107.8, -103.9, -106.9]
							},
							{
							"name": "Radiation, outgoing longwave",
							"unit": "W/m^2",
							"code": "LWOut_UnCor_NR01_Avg",
							"values": [-10.1, -10.59, -8.29, -7.361, -6.307, -4.767, 0.746, -0.032, 0.73, 0.649]
							},
							{
							"name": "Temperature, sensor",
							"unit": "degC",
							"code": "Temp_NR01_Avg",
							"values": [29.84, 29.96, 30.4, 30.87, 31.04, 31.35, 30.96, 30.83, 30.73, 31.12]
							},
							{
							"name": "Radiation, incoming shortwave",
							"unit": "W/m^2",
							"code": "SWIn_SP230_Avg",
							"values": [263.1, 246.0, 318.1, 372.2, 405.8, 418.7, 496.1, 486.3, 461.6, 424.9]
							},
							{
							"name": "Indicator",
							"unit": "code",
							"code": "Heater_on",
							"values": [0.0, 0.0, 0.0, 0.0, 0.0, 0.0, 0.0, 0.0, 0.0, 0.0]
							},
							{
							"name": "Temperature",
							"unit": "degC",
							"code": "DeltaTemp",
							"values": [34.2, 33.51, 33.45, 34.05, 32.3, 30.74, 29.17, 29.82, 29.68, 30.28]
							},
							{
							"name": "Radiation, incoming PAR",
							"unit": "umol/m^2 s",
							"code": "PARIn_Avg",
							"values": [480.1, 440.2, 580.7, 684.0, 750.3, 787.0, 945.0, 913.0, 865.0, 801.0]
							},
							{
							"name": "Radiation, outgoing PAR",
							"unit": "umol/m^2 s",
							"code": "PAROut_Avg",
							"values": [33.74, 31.11, 40.07, 46.85, 50.97, 53.23, 63.58, 61.39, 57.98, 53.84]
							},
							{
							"name": "Temperature",
							"unit": "degC",
							"code": "TargTemp_SI111_Avg",
							"values": [28.43, 28.43, 29.35, 30.01, 30.5, 31.05, 31.8, 31.31, 31.19, 31.35]
							},
							{
							"name": "Temperature, sensor",
							"unit": "degC",
							"code": "Temp_SI111_Avg",
							"values": [29.71, 29.77, 30.13, 30.56, 30.7, 31.03, 30.67, 30.51, 30.35, 30.68]
							},
							{
							"name": "Slope",
							"unit": "-",
							"code": "m_SI111",
							"values": [1555735000.0, 1555291000.0, 1557552000.0, 1561959000.0, 1566981000.0, 1566343000.0, 1572382000.0, 1565314000.0, 1564075000.0, 1563016000.0]
							},
							{
							"name": "Intercept",
							"unit": "-",
							"code": "b_SI111",
							"values": [3410426.0, 3395928.0, 3469806.0, 3613850.0, 3778178.0, 3757308.0, 3955152.0, 3723615.0, 3683074.0, 3648426.0]
							},
							{
							"name": "Voltage",
							"unit": "mV",
							"code": "TargV_SI111_Avg",
							"values": [-0.093, -0.098, -0.058, -0.041, -0.017, -0.001, 0.079, 0.056, 0.058, 0.046]
							},
							{
							"name": "Volumetric water content",
							"unit": "-",
							"code": "VWC_5cm_Avg",
							"values": [18.8, 18.86, 18.8, 18.74, 18.85, 18.86, 18.8, 18.86, 18.96, 18.86]
							},
							{
							"name": "Temperature",
							"unit": "degC",
							"code": "SoilTemp_5cm_Avg",
							"values": [18.99, 19.04, 19.04, 19.04, 19.02, 18.97, 18.93, 18.93, 18.88, 18.78]
							},
							{
							"name": "Bulk electrical conductivity",
							"unit": "dS/m",
							"code": "SoilCond_5cm_Avg",
							"values": [0.0, 0.0, 0.0, 0.0, 0.0, 0.0, 0.0, 0.0, 0.0, 0.0]
							},
							{
							"name": "Permittivity",
							"unit": "-",
							"code": "Permittivity_5cm_Avg",
							"values": [9.61, 9.64, 9.61, 9.57, 9.64, 9.64, 9.61, 9.64, 9.7, 9.64]
							},
							{
							"name": "Volumetric water content",
							"unit": "-",
							"code": "VWC_10cm_Avg",
							"values": [13.44, 13.38, 13.32, 13.32, 13.38, 13.38, 13.43, 13.26, 13.44, 13.44]
							},
							{
							"name": "Temperature",
							"unit": "degC",
							"code": "SoilTemp_10cm_Avg",
							"values": [18.25, 18.21, 18.16, 18.1, 18.05, 18.03, 17.94, 17.82, 17.73, 17.63]
							},
							{
							"name": "Bulk electrical conductivity",
							"unit": "dS/m",
							"code": "SoilCond_10cm_Avg",
							"values": [0.0, 0.0, 0.0, 0.0, 0.0, 0.0, 0.0, 0.0, 0.0, 0.0]
							},
							{
							"name": "Permittivity",
							"unit": "-",
							"code": "Permittivity_10cm_Avg",
							"values": [6.988, 6.96, 6.941, 6.94, 6.96, 6.96, 6.987, 6.912, 6.988, 6.989]
							},
							{
							"name": "Volumetric water content",
							"unit": "-",
							"code": "VWC_20cm_Avg",
							"values": [11.42, 11.53, 11.32, 11.36, 11.42, 11.26, 11.42, 11.54, 11.42, 11.65]
							},
							{
							"name": "Temperature",
							"unit": "degC",
							"code": "SoilTemp_20cm_Avg",
							"values": [16.76, 16.72, 16.65, 16.61, 16.54, 16.5, 16.46, 16.39, 16.32, 16.26]
							},
							{
							"name": "Bulk electrical conductivity",
							"unit": "dS/m",
							"code": "SoilCond_20cm_Avg",
							"values": [0.0, 0.0, 0.0, 0.0, 0.0, 0.0, 0.0, 0.0, 0.0, 0.0]
							},
							{
							"name": "Permittivity",
							"unit": "-",
							"code": "Permittivity_20cm_Avg",
							"values": [6.121, 6.167, 6.074, 6.1, 6.119, 6.053, 6.118, 6.169, 6.121, 6.216]
							},
							{
							"name": "Volumetric water content",
							"unit": "-",
							"code": "VWC_50cm_Avg",
							"values": [9.88, 9.99, 9.76, 9.75, 9.88, 9.88, 9.99, 9.93, 9.88, 10.05]
							},
							{
							"name": "Temperature",
							"unit": "degC",
							"code": "SoilTemp_50cm_Avg",
							"values": [13.45, 13.45, 13.45, 13.45, 13.45, 13.45, 13.43, 13.45, 13.43, 13.43]
							},
							{
							"name": "Bulk electrical conductivity",
							"unit": "dS/m",
							"code": "SoilCond_50cm_Avg",
							"values": [0.0, 0.0, 0.0, 0.0, 0.0, 0.0, 0.0, 0.0, 0.0, 0.0]
							},
							{
							"name": "Permittivity",
							"unit": "-",
							"code": "Permittivity_50cm_Avg",
							"values": [5.489, 5.538, 5.453, 5.451, 5.489, 5.491, 5.538, 5.52, 5.491, 5.557]
							},
							{
							"name": "Volumetric water content",
							"unit": "-",
							"code": "VWC_100cm_Avg",
							"values": [8.15, 8.15, 8.26, 8.15, 8.25, 8.31, 8.38, 8.26, 8.32, 8.26]
							},
							{
							"name": "Temperature",
							"unit": "degC",
							"code": "SoilTemp_100cm_Avg",
							"values": [8.93, 8.93, 8.93, 8.93, 8.93, 8.93, 8.93, 8.93, 8.93, 8.93]
							},
							{
							"name": "Bulk electrical conductivity",
							"unit": "dS/m",
							"code": "SoilCond_100cm_Avg",
							"values": [0.0, 0.0, 0.0, 0.0, 0.0, 0.0, 0.0, 0.0, 0.0, 0.0]
							},
							{
							"name": "Permittivity",
							"unit": "-",
							"code": "Permittivity_100cm_Avg",
							"values": [4.84, 4.84, 4.879, 4.841, 4.877, 4.898, 4.917, 4.881, 4.898, 4.879]
							},
							{
							"name": "Battery voltage",
							"unit": "V",
							"code": "BattVolt",
							"values": [12.8, 12.78, 12.8, 12.79, 12.79, 12.78, 12.76, 12.79, 12.77, 12.79]
							},
							{
							"name": "Temperature, datalogger",
							"unit": "degC",
							"code": "Panel_Temp",
							"values": [33.32, 33.7, 34.14, 34.44, 34.63, 34.81, 34.68, 34.74, 34.93, 35.37]
							},
							{
							"name": "Relative Humidity",
							"unit": "%",
							"code": "RH_enc",
							"values": [21.39, 22.06, 22.12, 22.17, 23.05, 23.66, 23.92, 23.78, 24.04, 24.14]
							},
							{
							"name": "Indicator",
							"unit": "code",
							"code": "Door_Tot",
							"values": [0.0, 0.0, 0.0, 0.0, 0.0, 0.0, 0.0, 0.0, 0.0, 0.0]
							},
							{
							"name": "Counter",
							"unit": "#",
							"code": "n",
							"values": [87.0, 87.0, 87.0, 87.0, 87.0, 87.0, 87.0, 87.0, 87.0, 87.0]
							},
							{
							"name": "Offset",
							"unit": "cm",
							"code": "JuddOffset",
							"values": [189.0, 189.0, 189.0, 189.0, 189.0, 189.0, 189.0, 189.0, 189.0, 189.0]
							},
							{
							"name": "Snow depth",
							"unit": "cm",
							"code": "JuddDepth_1",
							"values": [6.029, 6.326, 7.989, 5.502, 7.496, 6.749, 7.496, 5.549, 5.303, 4.685]
							},
							{
							"name": "Snow depth",
							"unit": "cm",
							"code": "JuddDepth_2",
							"values": [5.697, 5.787, 7.616, 7.286, 7.62, 6.915, 7.579, 5.466, 5.303, 5.639]
							},
							{
							"name": "Snow depth",
							"unit": "cm",
							"code": "JuddDepth_3",
							"values": [7.522, 7.031, 7.035, 6.622, 6.002, 5.712, 6.749, 8.62, 6.672, 5.017]
							},
							{
							"name": "Temperature",
							"unit": "degC",
							"code": "AirTemp_ST110_Avg",
							"values": [29.46, 29.5, 29.73, 30.08, 30.26, 30.2, 29.94, 29.8, 29.76, 29.78]
							},
							{
							"name": "Temperature",
							"unit": "degC",
							"code": "AirTemp_ST110_Max",
							"values": [29.67, 29.86, 30.13, 30.43, 30.55, 30.75, 30.68, 30.18, 29.94, 30.05]
							},
							{
							"name": "Temperature",
							"unit": "degC",
							"code": "AirTemp_ST110_Min",
							"values": [28.84, 29.23, 29.39, 29.83, 29.89, 29.92, 29.56, 29.62, 29.6, 29.6]
							},
							{
							"name": "Offset",
							"unit": "cm",
							"code": "Precip_offset",
							"values": [27.96, 27.96, 27.96, 27.96, 27.96, 27.96, 27.96, 27.96, 27.96, 27.96]
							},
							{
							"name": "Precipitation",
							"unit": "cm",
							"code": "Precip_HrDiff",
							"values": [0.0, 0.0, 0.0, 0.0, 0.0, 0.0, 0.0, 0.0, 0.0, 0.0]
							},
							{
							"name": "Evapotranspiration, potential",
							"unit": "mm",
							"code": "Evapotrans_ETr",
							"values": [0.666124, 0.6254381, 0.6561754, 0.6901627, 0.5909869, 0.5002773, 0.4551823, 0.5175213, 0.5403622, 0.5129059]
							},
							{
							"name": "Evapotranspiration, potential",
							"unit": "mm",
							"code": "Evapotrans_ETo",
							"values": [0.4070032, 0.3823352, 0.4047264, 0.4279466, 0.3728478, 0.3213137, 0.3003853, 0.335477, 0.3469175, 0.3287626]
							},
							{
							"name": "Temperature, sensor",
							"unit": "degC",
							"code": "InletTemp_avg",
							"values": [-242.0, -242.0, -242.0, -242.0, -242.0, -242.0, -242.0, -242.0, -242.0, -242.0]
							},
							{
							"name": "Frequency of rotation",
							"unit": "rpm",
							"code": "Tachometer_TS100",
							"values": [4502.0, 4500.0, 4495.0, 4497.0, 4501.0, 4501.0, 4502.0, 4497.0, 4496.0, 4495.0]
							},
							{
							"name": "Counter",
							"unit": "#",
							"code": "GeonorHeater_Tot",
							"values": [0.0, 0.0, 0.0, 0.0, 0.0, 0.0, 0.0, 0.0, 0.0, 0.0]
							},
							{
							"name": "Counter",
							"unit": "#",
							"code": "GeonorHeater_Manual_Tot",
							"values": [0.0, 0.0, 0.0, 0.0, 0.0, 0.0, 0.0, 0.0, 0.0, 0.0]
							}
					]

			},

			"RB_KF_BA": {
				"info": {
					"code": "RB_KF_BA",
					"name": "Knowlton Fork Basic Aquatic",
					"latitude": "40.809522",
					"longitude": "-111.765472",
					"lat_long_datum": "WGS84",
					"elevation": "1986.0768",
					"local_x": "None",
					"local_y": "None",
					"local_projection": "None",
					"pos_accuracy": "None",
					"state": "Utah",
					"county": "Salt Lake",
					"comments": "",
					"type": "Stream"
					},

				"update_time": {
					"min": "2013-08-30 11:30:00",
					"max": "2014-05-28 12:45:00"
					},

				"vars": [
							{
							"name": "Battery voltage",
							"unit": "V",
							"code": "BattVolt",
							"values": [13.52, 13.52, 13.57, 13.8, 13.98, 13.95, 14.0, 14.04, 14.08, 14.11]
							},
							{
							"name": "Relative Humidity",
							"unit": "%",
							"code": "RH_enc",
							"values": [19.25, 19.05, 18.68, 18.78, 17.5, 16.08, 15.14, 16.05, 15.14, 15.01]
							},
							{
							"name": "Indicator",
							"unit": "code",
							"code": "Door_Tot",
							"values": [0.0, 0.0, 0.0, 0.0, 0.0, 0.0, 0.0, 0.0, 0.0, 0.0]
							},
							{
							"name": "Temperature",
							"unit": "degC",
							"code": "WaterTemp_EXO",
							"values": [11.42, 11.38, 11.1, 10.85, 10.74, 10.58, 10.19, 9.84, 9.58, 9.3]
							},
							{
							"name": "Specific Conductance",
							"unit": "uS/cm",
							"code": "SpCond",
							"values": [544.3, 544.5, 545.0, 545.4, 545.9, 546.4, 547.1, 547.4, 548.2, 548.8]
							},
							{
							"name": "pH",
							"unit": "pH",
							"code": "pH",
							"values": [8.34, 8.34, 8.34, 8.34, 8.33, 8.33, 8.33, 8.33, 8.32, 8.32]
							},
							{
							"name": "Oxygen, dissolved",
							"unit": "mg/L",
							"code": "ODO",
							"values": [8.53, 8.56, 8.64, 8.68, 8.66, 8.71, 8.77, 8.84, 8.84, 8.96]
							},
							{
							"name": "Oxygen, dissolved percent of saturation",
							"unit": "% Sat",
							"code": "ODO_Sat",
							"values": [78.28, 78.39, 78.69, 78.59, 78.16, 78.32, 78.18, 78.12, 77.69, 78.24]
							},
							{
							"name": "Oxygen, dissolved, transducer signal",
							"unit": "% Sat",
							"code": "ODO_Local",
							"values": [97.7, 97.8, 98.2, 98.0, 97.5, 97.7, 97.5, 97.5, 96.9, 97.6]
							},
							{
							"name": "Time Stamp",
							"unit": "hhmm",
							"code": "EXOTime",
							"values": [194607.0, 193107.0, 191607.0, 190107.0, 184607.0, 183107.0, 181607.0, 180107.0, 174607.0, 173107.0]
							},
							{
							"name": "Electric Power",
							"unit": "V",
							"code": "EXOVolt",
							"values": [13.16, 13.15, 13.19, 13.37, 13.58, 13.59, 13.62, 13.67, 13.67, 13.73]
							},
							{
							"name": "Turbidity",
							"unit": "NTU",
							"code": "TurbAvg",
							"values": [5.3, 4.8, 4.71, 4.52, 4.75, 5.2, 5.23, 4.51, 4.86, 4.39]
							},
							{
							"name": "Turbidity",
							"unit": "NTU",
							"code": "TurbMed",
							"values": [5.2, 4.46, 4.37, 4.38, 4.4, 4.87, 4.7, 4.36, 4.5, 4.2]
							},
							{
							"name": "Turbidity",
							"unit": "NTU",
							"code": "TurbMin",
							"values": [2.87, 1.91, 1.41, 1.07, 2.66, 2.73, 1.58, 1.09, 2.54, 1.7]
							},
							{
							"name": "Turbidity",
							"unit": "NTU",
							"code": "TurbMax",
							"values": [8.69, 9.76, 12.94, 8.7, 10.61, 14.35, 16.28, 11.06, 10.2, 10.16]
							},
							{
							"name": "Turbidity",
							"unit": "NTU",
							"code": "TurbVar",
							"values": [1.457, 2.552, 3.895, 2.025, 2.483, 4.73, 5.521, 3.201, 2.12, 1.837]
							},
							{
							"name": "Turbidity",
							"unit": "NTU",
							"code": "TurbBES",
							"values": [5.2, 4.53, 4.36, 4.39, 4.42, 4.82, 4.79, 4.34, 4.65, 4.16]
							},
							{
							"name": "Temperature",
							"unit": "degC",
							"code": "WaterTemp_Turb",
							"values": [11.6, 11.5, 11.1, 10.9, 10.8, 10.6, 10.2, 9.9, 9.6, 9.3]
							},
							{
							"name": "Indicator",
							"unit": "code",
							"code": "TurbWipe",
							"values": [0.0, 0.0, 0.0, 0.0, 0.0, 0.0, 0.0, 0.0, 0.0, 0.0]
							},
							{
							"name": "Gage height",
							"unit": "cm",
							"code": "Stage",
							"values": [27.75, 27.73, 27.69, 27.65, 27.64, 27.57, 27.58, 27.51, 27.5, 27.48]
							},
							{
							"name": "Temperature",
							"unit": "degC",
							"code": "WaterTemp_PT",
							"values": [11.14, 10.99, 10.72, 10.51, 10.37, 10.1, 9.76, 9.45, 9.22, 8.9]
							},
							{
							"name": "Counter",
							"unit": "#",
							"code": "StageNaNCounter",
							"values": [0.0, 0.0, 0.0, 0.0, 0.0, 0.0, 0.0, 0.0, 0.0, 0.0]
							},
							{
							"name": "Offset",
							"unit": "cm",
							"code": "StageOffset",
							"values": [0.0, 0.0, 0.0, 0.0, 0.0, 0.0, 0.0, 0.0, 0.0, 0.0]
							}
					]

			},

			"RB_KF_C": {
				"info": {
					"code": "RB_KF_C",
					"name": "Knowlton Fork Climate",
					"latitude": "40.810122",
					"longitude": "-111.76695",
					"lat_long_datum": "WGS84",
					"elevation": "2178.1008",
					"local_x": "None",
					"local_y": "None",
					"local_projection": "None",
					"pos_accuracy": "None",
					"state": "Utah",
					"county": "Salt Lake",
					"comments": "",
					"type": "Atmosphere"
					},

				"update_time": {
					"min": "2013-07-10 14:15:00",
					"max": "2014-05-28 13:00:00"
					},

				"vars": [
							{
							"name": "Temperature",
							"unit": "degC",
							"code": "AirTemp_Avg",
							"values": [27.11, 26.88, 27.27, 26.45, 25.82, 26.21, 26.45, 26.13, 24.87, 25.21]
							},
							{
							"name": "Relative Humidity",
							"unit": "%",
							"code": "RH",
							"values": [19.09, 22.21, 18.25, 24.14, 23.31, 21.32, 20.09, 20.29, 21.69, 22.54]
							},
							{
							"name": "Temperature, dew point",
							"unit": "degC",
							"code": "DewPt_Avg",
							"values": [2.6, 2.706, 2.774, 2.906, 2.817, 2.144, 2.501, 2.472, 3.142, 2.64]
							},
							{
							"name": "Vapor pressure",
							"unit": "kPa",
							"code": "VaporPress_Avg",
							"values": [0.738, 0.744, 0.748, 0.755, 0.751, 0.715, 0.734, 0.732, 0.767, 0.74]
							},
							{
							"name": "Barometric pressure",
							"unit": "kPa",
							"code": "BP_Avg",
							"values": [79.77, 79.78, 79.81, 79.83, 79.85, 79.86, 79.87, 79.88, 79.9, 79.91]
							},
							{
							"name": "Wind speed",
							"unit": "m/s",
							"code": "WindSp_Avg",
							"values": [0.744, 0.657, 0.824, 0.876, 0.502, 0.786, 0.89, 0.701, 0.669, 0.834]
							},
							{
							"name": "Wind direction",
							"unit": "deg",
							"code": "WindDir_Avg",
							"values": [242.0, 230.0, 265.4, 230.6, 285.6, 259.9, 253.0, 258.5, 232.1, 228.5]
							},
							{
							"name": "Wind direction",
							"unit": "deg",
							"code": "WindDir_Std",
							"values": [54.69, 67.68, 70.6, 58.44, 54.61, 57.82, 57.4, 64.39, 71.6, 67.32]
							},
							{
							"name": "Precipitation",
							"unit": "cm",
							"code": "Precip_Tot_Avg",
							"values": [89.8, 89.8, 89.8, 89.8, 89.8, 89.8, 89.8, 89.8, 89.8, 89.8]
							},
							{
							"name": "Precipitation",
							"unit": "Hz",
							"code": "Precip_Freq_Avg",
							"values": [2152.0, 2152.0, 2152.0, 2152.0, 2152.0, 2152.0, 2152.0, 2153.0, 2153.0, 2153.0]
							},
							{
							"name": "Snow depth",
							"unit": "cm",
							"code": "JuddDepth_Avg",
							"values": [34.55, 33.48, 35.01, 29.26, 34.98, 31.0, 32.83, 33.31, 31.18, 32.63]
							},
							{
							"name": "Temperature",
							"unit": "degC",
							"code": "JuddTemp_Avg",
							"values": [29.08, 28.72, 29.19, 28.21, 27.71, 28.38, 28.09, 27.81, 26.06, 26.38]
							},
							{
							"name": "Radiation, incoming shortwave",
							"unit": "W/m^2",
							"code": "SWIn_NR01_Avg",
							"values": [952.0, 753.7, 952.0, 863.0, 709.6, 798.3, 967.0, 905.0, 755.6, 616.4]
							},
							{
							"name": "Radiation, outgoing shortwave",
							"unit": "W/m^2",
							"code": "SWOut_NR01_Avg",
							"values": [156.2, 122.7, 161.4, 145.3, 118.1, 135.9, 168.3, 158.6, 132.8, 107.0]
							},
							{
							"name": "Radiation, incoming longwave",
							"unit": "W/m^2",
							"code": "LWIn_Cor_NR01_Avg",
							"values": [360.7, 362.3, 353.2, 354.1, 354.5, 353.7, 347.3, 347.4, 342.7, 352.0]
							},
							{
							"name": "Radiation, outgoing longwave",
							"unit": "W/m^2",
							"code": "LWOut_Cor_NR01_Avg",
							"values": [544.6, 529.6, 551.9, 536.7, 513.2, 529.8, 544.4, 534.4, 503.8, 500.2]
							},
							{
							"name": "Radiation, net",
							"unit": "W/m^2",
							"code": "NetRad_NR01_Avg",
							"values": [611.7, 463.7, 592.1, 535.4, 432.8, 486.3, 601.4, 559.6, 461.6, 361.1]
							},
							{
							"name": "Radiation, incoming longwave",
							"unit": "W/m^2",
							"code": "LWIn_UnCor_NR01_Avg",
							"values": [-128.5, -126.5, -135.4, -129.2, -122.9, -129.2, -134.7, -131.6, -124.5, -117.3]
							},
							{
							"name": "Radiation, outgoing longwave",
							"unit": "W/m^2",
							"code": "LWOut_UnCor_NR01_Avg",
							"values": [55.48, 40.84, 63.39, 53.48, 35.76, 46.87, 62.43, 55.34, 36.68, 30.95]
							},
							{
							"name": "Temperature, sensor",
							"unit": "degC",
							"code": "Temp_NR01_Avg",
							"values": [31.62, 31.55, 31.51, 30.69, 29.77, 30.64, 30.49, 30.02, 28.13, 28.47]
							},
							{
							"name": "Radiation, incoming shortwave",
							"unit": "W/m^2",
							"code": "SWIn_SP230_Avg",
							"values": [941.0, 755.8, 941.0, 857.0, 711.3, 795.5, 952.0, 894.0, 748.2, 616.3]
							},
							{
							"name": "Indicator",
							"unit": "code",
							"code": "Heater_on",
							"values": [0.0, 0.0, 0.0, 0.0, 0.0, 0.0, 0.0, 0.0, 0.0, 0.0]
							},
							{
							"name": "Temperature",
							"unit": "degC",
							"code": "DeltaTemp",
							"values": [29.01, 28.85, 28.73, 27.78, 26.95, 28.51, 27.97, 27.54, 24.97, 25.82]
							},
							{
							"name": "Radiation, incoming PAR",
							"unit": "umol/m^2 s",
							"code": "PARIn_Avg",
							"values": [1792.0, 1439.0, 1808.0, 1635.0, 1354.0, 1513.0, 1817.0, 1694.0, 1416.0, 1155.0]
							},
							{
							"name": "Radiation, outgoing PAR",
							"unit": "umol/m^2 s",
							"code": "PAROut_Avg",
							"values": [99.4, 80.1, 103.5, 93.0, 76.66, 88.0, 106.9, 100.2, 84.4, 68.47]
							},
							{
							"name": "Temperature",
							"unit": "degC",
							"code": "TargTemp_SI111_Avg",
							"values": [41.37, 38.25, 41.94, 39.46, 35.38, 37.88, 40.34, 38.66, 33.97, 33.25]
							},
							{
							"name": "Temperature, sensor",
							"unit": "degC",
							"code": "Temp_SI111_Avg",
							"values": [31.71, 31.87, 31.45, 30.45, 29.58, 30.06, 29.88, 29.53, 27.82, 27.73]
							},
							{
							"name": "Slope",
							"unit": "-",
							"code": "m_SI111",
							"values": [1757146000.0, 1749701000.0, 1754496000.0, 1734893000.0, 1732563000.0, 1729478000.0, 1736285000.0, 1729891000.0, 1713182000.0, 1702614000.0]
							},
							{
							"name": "Intercept",
							"unit": "-",
							"code": "b_SI111",
							"values": [3296391.0, 3092222.0, 3223686.0, 2686633.0, 2622889.0, 2538491.0, 2724750.0, 2549774.0, 2093151.0, 1804783.0]
							},
							{
							"name": "Voltage",
							"unit": "mV",
							"code": "TargV_SI111_Avg",
							"values": [0.658, 0.428, 0.715, 0.607, 0.387, 0.526, 0.709, 0.615, 0.407, 0.368]
							},
							{
							"name": "Volumetric water content",
							"unit": "-",
							"code": "VWC_5cm_Avg",
							"values": [24.34, 24.4, 24.4, 1.123, 24.0, 24.35, 24.46, 24.56, 24.63, 24.69]
							},
							{
							"name": "Temperature",
							"unit": "degC",
							"code": "SoilTemp_5cm_Avg",
							"values": [20.5, 19.98, 19.42, 0.891, 17.99, 17.92, 17.53, 17.02, 16.54, 15.9]
							},
							{
							"name": "Bulk electrical conductivity",
							"unit": "dS/m",
							"code": "SoilCond_5cm_Avg",
							"values": [0.0, 0.0, 0.0, 0.0, 0.0, 0.0, 0.0, 0.0, 0.0, 0.0]
							},
							{
							"name": "Permittivity",
							"unit": "-",
							"code": "Permittivity_5cm_Avg",
							"values": [12.78, 12.81, 12.81, 0.59, 12.62, 12.78, 12.85, 12.92, 12.96, 12.99]
							},
							{
							"name": "Volumetric water content",
							"unit": "-",
							"code": "VWC_10cm_Avg",
							"values": [30.86, 31.02, 31.14, 31.09, 31.03, 31.03, 30.92, 31.19, 30.98, 31.03]
							},
							{
							"name": "Temperature",
							"unit": "degC",
							"code": "SoilTemp_10cm_Avg",
							"values": [14.62, 14.49, 14.38, 14.26, 14.15, 14.07, 14.03, 13.96, 13.92, 13.88]
							},
							{
							"name": "Bulk electrical conductivity",
							"unit": "dS/m",
							"code": "SoilCond_10cm_Avg",
							"values": [0.0, 0.0, 0.0, 0.0, 0.0, 0.0, 0.0, 0.0, 0.0, 0.0]
							},
							{
							"name": "Permittivity",
							"unit": "-",
							"code": "Permittivity_10cm_Avg",
							"values": [17.13, 17.26, 17.33, 17.3, 17.26, 17.26, 17.18, 17.37, 17.23, 17.26]
							},
							{
							"name": "Volumetric water content",
							"unit": "-",
							"code": "VWC_20cm_Avg",
							"values": [30.63, 30.69, 30.63, 30.69, 30.52, 30.63, 30.73, 30.74, 30.69, 30.85]
							},
							{
							"name": "Temperature",
							"unit": "degC",
							"code": "SoilTemp_20cm_Avg",
							"values": [13.3, 13.32, 13.27, 13.3, 13.27, 13.3, 13.27, 13.3, 13.32, 13.34]
							},
							{
							"name": "Bulk electrical conductivity",
							"unit": "dS/m",
							"code": "SoilCond_20cm_Avg",
							"values": [0.0, 0.0, 0.0, 0.0, 0.0, 0.0, 0.0, 0.0, 0.0, 0.0]
							},
							{
							"name": "Permittivity",
							"unit": "-",
							"code": "Permittivity_20cm_Avg",
							"values": [16.97, 17.01, 16.97, 17.01, 16.9, 16.97, 17.05, 17.05, 17.01, 17.12]
							},
							{
							"name": "Volumetric water content",
							"unit": "-",
							"code": "VWC_50cm_Avg",
							"values": [27.87, 27.87, 27.75, 27.75, 27.81, 27.75, 27.81, 27.81, 27.87, 27.81]
							},
							{
							"name": "Temperature",
							"unit": "degC",
							"code": "SoilTemp_50cm_Avg",
							"values": [10.37, 10.37, 10.37, 10.35, 10.35, 10.33, 10.35, 10.35, 10.33, 10.3]
							},
							{
							"name": "Bulk electrical conductivity",
							"unit": "dS/m",
							"code": "SoilCond_50cm_Avg",
							"values": [0.0, 0.0, 0.0, 0.0, 0.0, 0.0, 0.0, 0.0, 0.0, 0.0]
							},
							{
							"name": "Permittivity",
							"unit": "-",
							"code": "Permittivity_50cm_Avg",
							"values": [15.05, 15.05, 14.97, 14.97, 15.01, 14.97, 15.01, 15.01, 15.05, 15.01]
							},
							{
							"name": "Volumetric water content",
							"unit": "-",
							"code": "VWC_100cm_Avg",
							"values": [26.65, 26.72, 26.77, 26.88, 26.73, 26.77, 26.88, 26.77, 26.72, 26.77]
							},
							{
							"name": "Temperature",
							"unit": "degC",
							"code": "SoilTemp_100cm_Avg",
							"values": [7.27, 7.251, 7.251, 7.251, 7.25, 7.251, 7.27, 7.251, 7.25, 7.27]
							},
							{
							"name": "Bulk electrical conductivity",
							"unit": "dS/m",
							"code": "SoilCond_100cm_Avg",
							"values": [0.0, 0.0, 0.0, 0.0, 0.0, 0.0, 0.0, 0.0, 0.0, 0.0]
							},
							{
							"name": "Permittivity",
							"unit": "-",
							"code": "Permittivity_100cm_Avg",
							"values": [14.25, 14.28, 14.32, 14.4, 14.28, 14.32, 14.4, 14.32, 14.28, 14.32]
							},
							{
							"name": "Battery voltage",
							"unit": "V",
							"code": "BattVolt",
							"values": [13.15, 13.15, 13.14, 13.51, 13.5, 13.6, 13.56, 13.57, 13.67, 13.67]
							},
							{
							"name": "Temperature, datalogger",
							"unit": "degC",
							"code": "Panel_Temp",
							"values": [32.31, 32.26, 32.11, 31.6, 31.2, 31.25, 30.68, 29.66, 28.19, 27.44]
							},
							{
							"name": "Relative Humidity",
							"unit": "%",
							"code": "RH_enc",
							"values": [27.47, 26.99, 25.02, 25.23, 25.24, 23.49, 22.11, 22.15, 23.41, 23.68]
							},
							{
							"name": "Indicator",
							"unit": "code",
							"code": "Door_Tot",
							"values": [0.0, 0.0, 0.0, 0.0, 0.0, 0.0, 0.0, 0.0, 0.0, 0.0]
							},
							{
							"name": "Counter",
							"unit": "#",
							"code": "n",
							"values": [87.0, 87.0, 87.0, 87.0, 87.0, 87.0, 87.0, 87.0, 87.0, 87.0]
							},
							{
							"name": "Offset",
							"unit": "cm",
							"code": "JuddOffset",
							"values": [223.0, 223.0, 223.0, 223.0, 223.0, 223.0, 223.0, 223.0, 223.0, 223.0]
							},
							{
							"name": "Snow depth",
							"unit": "cm",
							"code": "JuddDepth_1",
							"values": [33.9, 35.05, 35.25, 35.37, 29.97, 34.08, 31.14, 34.46, 30.89, 32.35]
							},
							{
							"name": "Snow depth",
							"unit": "cm",
							"code": "JuddDepth_2",
							"values": [30.61, 34.89, 35.09, 35.04, 32.93, 35.44, 34.56, 35.03, 31.14, 31.77]
							},
							{
							"name": "Snow depth",
							"unit": "cm",
							"code": "JuddDepth_3",
							"values": [34.31, 35.26, 33.98, 34.96, 32.4, 35.35, 34.6, 32.56, 29.99, 32.89]
							},
							{
							"name": "Temperature",
							"unit": "degC",
							"code": "AirTemp_ST110_Avg",
							"values": [26.54, 26.22, 26.63, 25.86, 25.33, 25.46, 25.89, 25.53, 24.53, 24.57]
							},
							{
							"name": "Temperature",
							"unit": "degC",
							"code": "AirTemp_ST110_Max",
							"values": [28.75, 28.75, 28.84, 27.57, 27.63, 27.62, 28.83, 27.42, 26.34, 27.0]
							},
							{
							"name": "Temperature",
							"unit": "degC",
							"code": "AirTemp_ST110_Min",
							"values": [24.77, 24.92, 24.75, 24.28, 23.8, 24.04, 23.53, 23.75, 22.93, 22.55]
							},
							{
							"name": "Offset",
							"unit": "cm",
							"code": "Precip_offset",
							"values": [52.03, 52.03, 52.03, 52.03, 52.03, 52.03, 52.03, 52.03, 52.03, 52.03]
							},
							{
							"name": "Precipitation",
							"unit": "cm",
							"code": "Precip_HrDiff",
							"values": [0.0, 0.0, 0.0, 0.0, 0.0, 0.0, 0.0, 0.0, 0.0, 0.0]
							},
							{
							"name": "Evapotranspiration, potential",
							"unit": "mm",
							"code": "Evapotrans_ETr",
							"values": [0.2653356, 0.2188695, 0.2726502, 0.2559297, 0.1924565, 0.2360707, 0.2770331, 0.2479402, 0.2099178, 0.1993488]
							},
							{
							"name": "Evapotranspiration, potential",
							"unit": "mm",
							"code": "Evapotrans_ETo",
							"values": [0.2236424, 0.1831544, 0.2278513, 0.2113285, 0.1641004, 0.1953851, 0.2303947, 0.2094134, 0.1760113, 0.1605824]
							},
							{
							"name": "Temperature, sensor",
							"unit": "degC",
							"code": "InletTemp_avg",
							"values": [-242.0, -242.0, -242.0, -242.0, -242.0, -242.0, -242.0, -242.0, -242.0, -242.0]
							},
							{
							"name": "Frequency of rotation",
							"unit": "rpm",
							"code": "Tachometer_TS100",
							"values": [4843.0, 4840.0, 4914.0, 4974.0, 4968.0, 4964.0, 4972.0, 4980.0, 4994.0, 5001.0]
							},
							{
							"name": "Counter",
							"unit": "#",
							"code": "GeonorHeater_Tot",
							"values": [0.0, 0.0, 0.0, 0.0, 0.0, 0.0, 0.0, 0.0, 0.0, 0.0]
							},
							{
							"name": "Counter",
							"unit": "#",
							"code": "GeonorHeater_Manual_Tot",
							"values": [0.0, 0.0, 0.0, 0.0, 0.0, 0.0, 0.0, 0.0, 0.0, 0.0]
							}
					]

			},

			"RB_KF_R": {
				"info": {
					"code": "RB_KF_R",
					"name": "Knowlton Fork Repeater",
					"latitude": "40.816219",
					"longitude": "-111.76695",
					"lat_long_datum": "WGS84",
					"elevation": "2215.896",
					"local_x": "None",
					"local_y": "None",
					"local_projection": "None",
					"pos_accuracy": "None",
					"state": "Utah",
					"county": "Salt Lake",
					"comments": "",
					"type": "Land"
					},

				"update_time": {
					"min": "None",
					"max": "None"
					},

				"vars": [

					]

			},

			"RB_KF_S": {
				"info": {
					"code": "RB_KF_S",
					"name": "Knowlton Fork Sapflux",
					"latitude": "40.810086",
					"longitude": "-111.769412",
					"lat_long_datum": "WGS84",
					"elevation": "2074.164",
					"local_x": "None",
					"local_y": "None",
					"local_projection": "None",
					"pos_accuracy": "None",
					"state": "Utah",
					"county": "Salt Lake",
					"comments": "",
					"type": "Land"
					},

				"update_time": {
					"min": "2013-09-10 13:45:00",
					"max": "2013-10-18 08:45:00"
					},

				"vars": [
							{
							"name": "Temperature",
							"unit": "degC",
							"code": "AirTemp_Avg",
							"values": [2.577, 1.625, 1.052, 0.576, 0.386, -0.157, -0.839, -0.987, -0.687, -0.693]
							},
							{
							"name": "Relative Humidity",
							"unit": "%",
							"code": "RH",
							"values": [61.99, 67.52, 69.73, 66.48, 72.18, 74.08, 69.84, 73.94, 71.57, 73.94]
							},
							{
							"name": "Temperature, dew point",
							"unit": "degC",
							"code": "DewPt_Avg",
							"values": [-3.966, -3.64, -4.026, -4.019, -4.133, -4.709, -5.096, -5.124, -5.114, -5.076]
							}
					]

			},

			"RB_RBG_BA": {
				"info": {
					"code": "RB_RBG_BA",
					"name": "Red Butte Gate Basic Aquatic",
					"latitude": "40.774228",
					"longitude": "-111.817025",
					"lat_long_datum": "WGS84",
					"elevation": "1582.2168",
					"local_x": "None",
					"local_y": "None",
					"local_projection": "None",
					"pos_accuracy": "None",
					"state": "Utah",
					"county": "Salt Lake",
					"comments": "",
					"type": "Stream"
					},

				"update_time": {
					"min": "2014-01-23 16:00:00",
					"max": "2014-05-28 15:45:00"
					},

				"vars": [
							{
							"name": "Battery voltage",
							"unit": "V",
							"code": "BattVolt",
							"values": [13.74, 13.86, 13.93, 13.99, 13.97, 14.04, 14.05, 14.0, 13.96, 14.0]
							},
							{
							"name": "Relative Humidity",
							"unit": "%",
							"code": "RH_enc",
							"values": [25.48, 25.14, 24.87, 24.53, 24.19, 24.16, 24.06, 23.86, 23.31, 22.23]
							},
							{
							"name": "Indicator",
							"unit": "code",
							"code": "Door_Tot",
							"values": [0.0, 0.0, 0.0, 0.0, 0.0, 0.0, 0.0, 0.0, 0.0, 0.0]
							},
							{
							"name": "Temperature",
							"unit": "degC",
							"code": "WaterTemp_EXO",
							"values": [10.43, 10.49, 10.55, 10.63, 10.67, 10.76, 10.76, 10.79, 10.94, 11.13]
							},
							{
							"name": "Specific Conductance",
							"unit": "uS/cm",
							"code": "SpCond",
							"values": [576.0, 574.4, 574.2, 574.9, 575.5, 576.2, 573.9, 574.0, 572.1, 570.0]
							},
							{
							"name": "pH",
							"unit": "pH",
							"code": "pH",
							"values": [8.54, 8.54, 8.55, 8.55, 8.55, 8.56, 8.56, 8.56, 8.57, 8.57]
							},
							{
							"name": "Oxygen, dissolved",
							"unit": "mg/L",
							"code": "ODO",
							"values": [9.19, 9.22, 9.25, 9.28, 9.25, 9.3, 9.3, 9.25, 9.2, 9.2]
							},
							{
							"name": "Oxygen, dissolved percent of saturation",
							"unit": "% Sat",
							"code": "ODO_Sat",
							"values": [82.4, 82.8, 83.2, 83.5, 83.4, 84.0, 84.0, 83.7, 83.5, 83.9]
							},
							{
							"name": "Oxygen, dissolved, transducer signal",
							"unit": "% Sat",
							"code": "ODO_Local",
							"values": [98.4, 98.8, 99.3, 99.7, 99.5, 100.3, 100.3, 99.9, 99.7, 100.1]
							},
							{
							"name": "Time Stamp",
							"unit": "hhmm",
							"code": "EXOTime",
							"values": [224746.0, 223246.0, 221746.0, 220246.0, 214746.0, 213246.0, 211746.0, 210246.0, 204746.0, 203246.0]
							},
							{
							"name": "Electric Power",
							"unit": "V",
							"code": "EXOVolt",
							"values": [13.31, 13.42, 13.48, 13.55, 13.52, 13.61, 13.61, 13.54, 13.54, 13.55]
							},
							{
							"name": "Turbidity",
							"unit": "NTU",
							"code": "TurbAvg",
							"values": [20.55, 22.3, 21.58, 21.06, 22.46, 22.8, 21.93, 20.98, 21.16, 22.12]
							},
							{
							"name": "Turbidity",
							"unit": "NTU",
							"code": "TurbMed",
							"values": [20.19, 22.14, 21.18, 20.78, 22.35, 22.24, 21.72, 20.84, 20.93, 22.01]
							},
							{
							"name": "Turbidity",
							"unit": "NTU",
							"code": "TurbMin",
							"values": [16.75, 17.48, 18.0, 16.79, 18.68, 19.78, 18.39, 17.56, 17.08, 18.36]
							},
							{
							"name": "Turbidity",
							"unit": "NTU",
							"code": "TurbMax",
							"values": [30.82, 28.66, 27.65, 29.23, 31.92, 34.8, 35.75, 25.42, 35.47, 36.13]
							},
							{
							"name": "Turbidity",
							"unit": "NTU",
							"code": "TurbVar",
							"values": [4.922, 5.727, 3.684, 6.055, 3.656, 7.89, 5.905, 3.415, 5.501, 5.36]
							},
							{
							"name": "Turbidity",
							"unit": "NTU",
							"code": "TurbBES",
							"values": [20.21, 22.15, 21.31, 20.83, 22.35, 22.19, 21.67, 20.88, 20.86, 21.95]
							},
							{
							"name": "Temperature",
							"unit": "degC",
							"code": "WaterTemp_Turb",
							"values": [10.5, 10.6, 10.6, 10.7, 10.8, 10.8, 10.8, 10.9, 11.1, 11.2]
							},
							{
							"name": "Indicator",
							"unit": "code",
							"code": "TurbWipe",
							"values": [0.0, 0.0, 0.0, 0.0, 0.0, 0.0, 0.0, 0.0, 0.0, 0.0]
							},
							{
							"name": "Gage height",
							"unit": "cm",
							"code": "Stage",
							"values": [40.62, 40.62, 40.63, 40.64, 40.65, 40.65, 40.67, 40.66, 40.69, 40.68]
							},
							{
							"name": "Temperature",
							"unit": "degC",
							"code": "WaterTemp_PT",
							"values": [10.38, 10.45, 10.5, 10.58, 10.63, 10.7, 10.7, 10.77, 10.92, 11.13]
							},
							{
							"name": "Counter",
							"unit": "#",
							"code": "StageNaNCounter",
							"values": [0.0, 0.0, 0.0, 0.0, 0.0, 0.0, 0.0, 0.0, 0.0, 0.0]
							},
							{
							"name": "Offset",
							"unit": "cm",
							"code": "StageOffset",
							"values": [0.0, 0.0, 0.0, 0.0, 0.0, 0.0, 0.0, 0.0, 0.0, 0.0]
							}
					]

			},

			"RB_TM_C": {
				"info": {
					"code": "RB_TM_C",
					"name": "Todds Meadow Climate",
					"latitude": "40.789054",
					"longitude": "-111.796416",
					"lat_long_datum": "WGS84",
					"elevation": "1763.0",
					"local_x": "None",
					"local_y": "None",
					"local_projection": "None",
					"pos_accuracy": "None",
					"state": "Utah",
					"county": "Salt Lake",
					"comments": "None",
					"type": "Atmosphere"
					},

				"update_time": {
					"min": "2013-11-18 15:00:00",
					"max": "2014-05-28 13:00:00"
					},

				"vars": [
							{
							"name": "Temperature",
							"unit": "degC",
							"code": "AirTemp_Avg",
							"values": [-2.807, -1.579, -1.479, -1.373, -1.183, -0.887, -0.974, -0.899, -0.8, -0.733]
							},
							{
							"name": "Relative Humidity",
							"unit": "%",
							"code": "RH",
							"values": [17.33, 19.66, 18.9, 22.84, 20.45, 21.28, 21.52, 21.69, 20.18, 28.82]
							},
							{
							"name": "Temperature, dew point",
							"unit": "degC",
							"code": "DewPt_Avg",
							"values": [2.283, 2.521, 2.468, 2.898, 2.618, 1.839, 2.552, 2.152, 2.969, 3.036]
							},
							{
							"name": "Vapor pressure",
							"unit": "kPa",
							"code": "VaporPress_Avg",
							"values": [0.722, 0.735, 0.732, 0.756, 0.74, 0.699, 0.737, 0.716, 0.761, 0.764]
							},
							{
							"name": "Barometric pressure",
							"unit": "kPa",
							"code": "BP_Avg",
							"values": [82.1, 82.1, 82.1, 82.2, 82.2, 82.2, 82.2, 82.2, 82.2, 82.2]
							},
							{
							"name": "Wind speed",
							"unit": "m/s",
							"code": "WindSp_Avg",
							"values": [2.08, 1.566, 2.026, 1.599, 1.551, 1.809, 1.787, 1.415, 1.47, 0.932]
							},
							{
							"name": "Wind direction",
							"unit": "deg",
							"code": "WindDir_Avg",
							"values": [115.4, 179.2, 172.9, 188.3, 165.3, 177.0, 172.1, 159.2, 126.2, 147.3]
							},
							{
							"name": "Wind direction",
							"unit": "deg",
							"code": "WindDir_Std",
							"values": [84.7, 74.46, 53.55, 55.1, 57.48, 51.3, 67.97, 50.52, 73.08, 82.7]
							},
							{
							"name": "Precipitation",
							"unit": "cm",
							"code": "Precip_Tot_Avg",
							"values": [55.09, 55.1, 55.1, 55.1, 55.1, 55.1, 55.1, 55.1, 55.1, 55.11]
							},
							{
							"name": "Precipitation",
							"unit": "Hz",
							"code": "Precip_Freq_Avg",
							"values": [2073.0, 2073.0, 2073.0, 2073.0, 2073.0, 2073.0, 2073.0, 2073.0, 2073.0, 2073.0]
							},
							{
							"name": "Snow depth",
							"unit": "cm",
							"code": "JuddDepth_Avg",
							"values": [13.24, 10.62, 12.76, 8.71, 2.979, 8.76, 11.75, 12.43, 12.35, 8.35]
							},
							{
							"name": "Temperature",
							"unit": "degC",
							"code": "JuddTemp_Avg",
							"values": [27.5, 27.46, 27.09, 26.93, 26.02, 25.98, 26.93, 26.54, 25.05, 26.33]
							},
							{
							"name": "Radiation, incoming shortwave",
							"unit": "W/m^2",
							"code": "SWIn_NR01_Avg",
							"values": [996.0, 795.1, 940.0, 876.0, 855.0, 792.6, 924.0, 907.0, 893.0, 533.8]
							},
							{
							"name": "Radiation, outgoing shortwave",
							"unit": "W/m^2",
							"code": "SWOut_NR01_Avg",
							"values": [169.2, 134.0, 158.2, 148.2, 146.5, 135.0, 156.9, 156.0, 155.4, 89.7]
							},
							{
							"name": "Radiation, incoming longwave",
							"unit": "W/m^2",
							"code": "LWIn_Cor_NR01_Avg",
							"values": [355.4, 357.5, 347.8, 349.5, 350.1, 347.8, 342.9, 341.5, 338.6, 348.8]
							},
							{
							"name": "Radiation, outgoing longwave",
							"unit": "W/m^2",
							"code": "LWOut_Cor_NR01_Avg",
							"values": [493.4, 481.2, 491.8, 482.9, 475.5, 474.3, 482.9, 476.0, 466.8, 452.0]
							},
							{
							"name": "Radiation, net",
							"unit": "W/m^2",
							"code": "NetRad_NR01_Avg",
							"values": [688.5, 537.4, 637.4, 594.3, 582.7, 531.1, 626.7, 616.7, 609.8, 341.0]
							},
							{
							"name": "Radiation, incoming longwave",
							"unit": "W/m^2",
							"code": "LWIn_UnCor_NR01_Avg",
							"values": [-122.5, -118.0, -128.6, -124.2, -117.6, -121.0, -131.3, -127.3, -126.1, -116.5]
							},
							{
							"name": "Radiation, outgoing longwave",
							"unit": "W/m^2",
							"code": "LWOut_UnCor_NR01_Avg",
							"values": [15.45, 5.793, 15.41, 9.28, 7.795, 5.51, 8.7, 7.176, 2.02, -13.34]
							},
							{
							"name": "Temperature, sensor",
							"unit": "degC",
							"code": "Temp_NR01_Avg",
							"values": [29.85, 29.46, 29.61, 29.17, 28.22, 28.4, 29.25, 28.4, 27.74, 27.84]
							},
							{
							"name": "Radiation, incoming shortwave",
							"unit": "W/m^2",
							"code": "SWIn_SP230_Avg",
							"values": [989.0, 790.5, 928.0, 871.0, 851.0, 785.5, 907.0, 893.0, 878.0, 533.5]
							},
							{
							"name": "Indicator",
							"unit": "code",
							"code": "Heater_on",
							"values": [0.0, 0.0, 0.0, 0.0, 0.0, 0.0, 0.0, 0.0, 0.0, 0.0]
							},
							{
							"name": "Temperature",
							"unit": "degC",
							"code": "DeltaTemp",
							"values": [27.56, 26.94, 27.14, 26.27, 25.6, 26.56, 26.7, 26.24, 24.76, 24.81]
							},
							{
							"name": "Radiation, incoming PAR",
							"unit": "umol/m^2 s",
							"code": "PARIn_Avg",
							"values": [1819.0, 1466.0, 1734.0, 1630.0, 1584.0, 1463.0, 1702.0, 1670.0, 1643.0, 1001.0]
							},
							{
							"name": "Radiation, outgoing PAR",
							"unit": "umol/m^2 s",
							"code": "PAROut_Avg",
							"values": [94.4, 75.35, 89.8, 83.7, 81.0, 74.86, 87.3, 85.3, 83.6, 50.56]
							},
							{
							"name": "Temperature",
							"unit": "degC",
							"code": "TargTemp_SI111_Avg",
							"values": [34.59, 32.18, 33.91, 32.31, 30.95, 30.51, 31.99, 30.76, 28.92, 26.29]
							},
							{
							"name": "Temperature, sensor",
							"unit": "degC",
							"code": "Temp_SI111_Avg",
							"values": [29.82, 29.52, 29.66, 29.07, 28.03, 28.18, 29.17, 28.13, 27.48, 27.56]
							},
							{
							"name": "Slope",
							"unit": "-",
							"code": "m_SI111",
							"values": [1602894000.0, 1593386000.0, 1596341000.0, 1592748000.0, 1588805000.0, 1580479000.0, 1583507000.0, 1585239000.0, 1580191000.0, 1569735000.0]
							},
							{
							"name": "Intercept",
							"unit": "-",
							"code": "b_SI111",
							"values": [5176951.0, 4896594.0, 4983733.0, 4877788.0, 4761494.0, 4515836.0, 4605193.0, 4656292.0, 4507336.0, 4198685.0]
							},
							{
							"name": "Voltage",
							"unit": "mV",
							"code": "TargV_SI111_Avg",
							"values": [0.338, 0.185, 0.3, 0.226, 0.204, 0.161, 0.196, 0.182, 0.098, -0.089]
							},
							{
							"name": "Volumetric water content",
							"unit": "-",
							"code": "VWC_5cm_Avg",
							"values": [20.79, 20.9, 20.91, 20.8, 20.69, 20.84, 20.69, 20.79, 20.73, 21.06]
							},
							{
							"name": "Temperature",
							"unit": "degC",
							"code": "SoilTemp_5cm_Avg",
							"values": [19.69, 19.25, 18.86, 18.49, 18.01, 17.53, 17.11, 16.76, 16.41, 16.14]
							},
							{
							"name": "Bulk electrical conductivity",
							"unit": "dS/m",
							"code": "SoilCond_5cm_Avg",
							"values": [0.0, 0.0, 0.0, 0.0, 0.0, 0.0, 0.0, 0.0, 0.0, 0.0]
							},
							{
							"name": "Permittivity",
							"unit": "-",
							"code": "Permittivity_5cm_Avg",
							"values": [10.69, 10.75, 10.75, 10.69, 10.62, 10.72, 10.63, 10.69, 10.66, 10.84]
							},
							{
							"name": "Volumetric water content",
							"unit": "-",
							"code": "VWC_10cm_Avg",
							"values": [19.27, 19.27, 19.27, 19.27, 19.27, 19.38, 19.27, 19.37, 19.27, 19.33]
							},
							{
							"name": "Temperature",
							"unit": "degC",
							"code": "SoilTemp_10cm_Avg",
							"values": [17.22, 16.93, 16.62, 16.31, 16.05, 15.85, 15.63, 15.47, 15.32, 15.21]
							},
							{
							"name": "Bulk electrical conductivity",
							"unit": "dS/m",
							"code": "SoilCond_10cm_Avg",
							"values": [0.0, 0.0, 0.0, 0.0, 0.0, 0.0, 0.0, 0.0, 0.0, 0.0]
							},
							{
							"name": "Permittivity",
							"unit": "-",
							"code": "Permittivity_10cm_Avg",
							"values": [9.85, 9.85, 9.85, 9.85, 9.85, 9.92, 9.85, 9.92, 9.85, 9.89]
							},
							{
							"name": "Volumetric water content",
							"unit": "-",
							"code": "VWC_20cm_Avg",
							"values": [21.49, 21.54, 21.54, 21.54, 21.54, 21.54, 21.61, 21.49, 21.54, 21.49]
							},
							{
							"name": "Temperature",
							"unit": "degC",
							"code": "SoilTemp_20cm_Avg",
							"values": [14.16, 14.16, 14.16, 14.16, 14.14, 14.16, 14.16, 14.19, 14.16, 14.19]
							},
							{
							"name": "Bulk electrical conductivity",
							"unit": "dS/m",
							"code": "SoilCond_20cm_Avg",
							"values": [0.0, 0.0, 0.0, 0.0, 0.0, 0.0, 0.0, 0.0, 0.0, 0.0]
							},
							{
							"name": "Permittivity",
							"unit": "-",
							"code": "Permittivity_20cm_Avg",
							"values": [11.08, 11.12, 11.12, 11.12, 11.12, 11.12, 11.15, 11.08, 11.12, 11.08]
							},
							{
							"name": "Volumetric water content",
							"unit": "-",
							"code": "VWC_50cm_Avg",
							"values": [21.84, 22.12, 22.01, 21.96, 22.01, 22.08, 22.08, 22.08, 21.79, 22.0]
							},
							{
							"name": "Temperature",
							"unit": "degC",
							"code": "SoilTemp_50cm_Avg",
							"values": [11.82, 11.82, 11.82, 11.82, 11.82, 11.82, 11.8, 11.8, 11.8, 11.8]
							},
							{
							"name": "Bulk electrical conductivity",
							"unit": "dS/m",
							"code": "SoilCond_50cm_Avg",
							"values": [0.0, 0.0, 0.0, 0.0, 0.0, 0.0, 0.0, 0.0, 0.0, 0.0]
							},
							{
							"name": "Permittivity",
							"unit": "-",
							"code": "Permittivity_50cm_Avg",
							"values": [11.28, 11.44, 11.39, 11.35, 11.39, 11.42, 11.42, 11.42, 11.26, 11.39]
							},
							{
							"name": "Volumetric water content",
							"unit": "-",
							"code": "VWC_100cm_Avg",
							"values": [17.77, 18.03, 18.03, 17.98, 17.92, 17.86, 17.92, 17.86, 17.92, 17.86]
							},
							{
							"name": "Temperature",
							"unit": "degC",
							"code": "SoilTemp_100cm_Avg",
							"values": [8.89, 8.98, 8.95, 8.98, 8.95, 8.98, 8.98, 8.95, 8.98, 8.98]
							},
							{
							"name": "Bulk electrical conductivity",
							"unit": "dS/m",
							"code": "SoilCond_100cm_Avg",
							"values": [0.0, 0.0, 0.0, 0.0, 0.0, 0.0, 0.0, 0.0, 0.0, 0.0]
							},
							{
							"name": "Permittivity",
							"unit": "-",
							"code": "Permittivity_100cm_Avg",
							"values": [9.07, 9.21, 9.21, 9.18, 9.15, 9.12, 9.15, 9.12, 9.15, 9.12]
							},
							{
							"name": "Battery voltage",
							"unit": "V",
							"code": "BattVolt",
							"values": [13.17, 13.15, 13.53, 13.59, 13.62, 13.58, 13.52, 13.61, 13.67, 13.62]
							},
							{
							"name": "Temperature, datalogger",
							"unit": "degC",
							"code": "Panel_Temp",
							"values": [30.38, 30.31, 30.35, 29.99, 29.56, 29.58, 29.53, 28.67, 27.77, 27.07]
							},
							{
							"name": "Relative Humidity",
							"unit": "%",
							"code": "RH_enc",
							"values": [30.62, 32.49, 31.78, 33.24, 33.18, 33.1, 32.89, 33.4, 34.38, 36.79]
							},
							{
							"name": "Indicator",
							"unit": "code",
							"code": "Door_Tot",
							"values": [0.0, 0.0, 0.0, 0.0, 0.0, 0.0, 0.0, 0.0, 0.0, 0.0]
							},
							{
							"name": "Counter",
							"unit": "#",
							"code": "n",
							"values": [7999.0, 7999.0, 7999.0, 7999.0, 7999.0, 7999.0, 7999.0, 7999.0, 7999.0, 7999.0]
							},
							{
							"name": "Offset",
							"unit": "cm",
							"code": "JuddOffset",
							"values": [253.0, 253.0, 253.0, 253.0, 253.0, 253.0, 253.0, 253.0, 253.0, 253.0]
							},
							{
							"name": "Snow depth",
							"unit": "cm",
							"code": "JuddDepth_1",
							"values": [14.5, 9.97, 10.79, 12.18, 8.11, 3.782, 11.88, 14.09, 8.15, 12.49]
							},
							{
							"name": "Snow depth",
							"unit": "cm",
							"code": "JuddDepth_2",
							"values": [13.76, 13.76, 9.02, 4.817, 2.716, 3.988, 11.84, 13.76, 6.624, 11.95]
							},
							{
							"name": "Snow depth",
							"unit": "cm",
							"code": "JuddDepth_3",
							"values": [13.1, 8.7, 11.24, 6.34, 1.975, 3.988, 11.22, 16.43, 11.89, 13.31]
							},
							{
							"name": "Temperature",
							"unit": "degC",
							"code": "AirTemp_ST110_Avg",
							"values": [27.07, 26.45, 26.56, 26.05, 25.6, 25.53, 25.81, 25.37, 24.9, 24.51]
							},
							{
							"name": "Temperature",
							"unit": "degC",
							"code": "AirTemp_ST110_Max",
							"values": [27.76, 27.27, 27.18, 26.54, 26.59, 26.34, 26.99, 26.18, 25.69, 25.88]
							},
							{
							"name": "Temperature",
							"unit": "degC",
							"code": "AirTemp_ST110_Min",
							"values": [26.4, 25.51, 26.12, 25.62, 24.53, 24.62, 25.01, 24.33, 23.93, 23.39]
							},
							{
							"name": "Offset",
							"unit": "cm",
							"code": "Precip_offset",
							"values": [29.22, 29.22, 29.22, 29.22, 29.22, 29.22, 29.22, 29.22, 29.22, 29.22]
							},
							{
							"name": "Precipitation",
							"unit": "cm",
							"code": "Precip_HrDiff",
							"values": [0.0, 0.0, 0.0, 0.0, 0.0, 0.0, 0.0, 0.0, 0.0, 0.0]
							},
							{
							"name": "Evapotranspiration, potential",
							"unit": "mm",
							"code": "Evapotrans_ETr",
							"values": [0.3886127, 0.3028369, 0.3679545, 0.316984, 0.3065553, 0.3170226, 0.3385791, 0.3036793, 0.2990521, 0.1884434]
							},
							{
							"name": "Evapotranspiration, potential",
							"unit": "mm",
							"code": "Evapotrans_ETo",
							"values": [0.2951747, 0.2321021, 0.2786953, 0.2454156, 0.2376494, 0.2389645, 0.2599404, 0.2389216, 0.2346294, 0.1474168]
							},
							{
							"name": "Temperature, sensor",
							"unit": "degC",
							"code": "InletTemp_avg",
							"values": [-242.0, -242.0, -242.0, -242.0, -242.0, -242.0, -242.0, -242.0, -242.0, -242.0]
							},
							{
							"name": "Frequency of rotation",
							"unit": "rpm",
							"code": "Tachometer_TS100",
							"values": [4785.0, 4837.0, 4909.0, 4908.0, 4907.0, 4908.0, 4907.0, 4901.0, 4920.0, 4925.0]
							},
							{
							"name": "Counter",
							"unit": "#",
							"code": "GeonorHeater_Tot",
							"values": [0.0, 0.0, 0.0, 0.0, 0.0, 0.0, 0.0, 0.0, 0.0, 0.0]
							},
							{
							"name": "Counter",
							"unit": "#",
							"code": "GeonorHeater_Manual_Tot",
							"values": [0.0, 0.0, 0.0, 0.0, 0.0, 0.0, 0.0, 0.0, 0.0, 0.0]
							}
					]

			}

}